{
  "source": "downloaded_pdfs/bn178-2019.pdf",
  "processed_date": "2025-04-22T19:19:06.985336",
  "document_info": {
    "title": null
  },
  "total_pages": 22,
  "chunks": [
    {
      "text": "BERITA NEGARA REPUBLIK INDONESIA No.178, 2019 KEMENDAG. Wakil Pemerintah Pusat . Penyelenggaraan Dekonsentrasi . TA 2019. Pelimpahan Urusan Pemerintahan . Bidang Perdagangan . PERATURAN MENTERI PERDAGANGAN REPUBLIK INDONESIA NOMOR 06 TAHUN 2019 TENTANG PELIMPAHAN SEBAGIAN URUSAN PEMERINTAHAN DI BIDANG PERDAGANGAN KEPADA GUBERNUR SEBAGAI WAKIL PEMERINTAH PUSAT DALAM RANGKA PENYELENGGARAAN DEKONSENTRASI TAHUN ANGGARAN 201 9 DENGAN RAHMAT TUHAN YANG MAHA ESA MENTERI PERDAGANGAN REPUBL IK INDONESIA, Menimbang : bahwa untuk melaksanakan ketentuan Pasal 16 ayat (5) Peraturan Pemerintah Nomor 7 Tahun 2008 tentang Dekonsentrasi dan Tugas Pembantuan, perlu menetapkan Peraturan Menteri Perdagangan tentang Pelimpahan Sebagian Urusan Pemerinta han di Bidang Perdagangan Kepada Gubernur Sebagai Wakil Pemerintah Pusat Dalam Rangka Penyelenggaraan Dekonsentrasi Tahun Anggaran 201 9; Mengingat : 1. Undang -Undang Nomor 17 Tahun 2003 tentang Keuangan Negara (Lembaran Negara Republik lndonesia Tahun 200 3 Nomor 47, Tambahan Lembaran Negara Republik lndonesia Nomor 4286); 2. Undang -Undang Nomor 1 Tahun 2004 tentang Perbendaharaan Negara (Lembaran Negara Republik Indonesia Tahun 2004 Nomor 5, Tambahan Lembaran www.peraturan.go.id 2019, No.178 -2- Negara Republik Indonesia Nomor 4355); 3. Undang -Undang Nomor 33 Tahun 2004 tentang Perimbangan Keuangan antara Pemerintah Pusat dan Pemerintah Daerah (Lembaran Negara Republik Indonesia Tahun 2004 Nomor 126, Tambahan Lembaran Negara Republik Indonesia Nomor 4438); 4. Undang -Undang Nomor 7 Tahun 2014 tentang Perdagangan (Lembaran Negara Republik Indonesia Tahun 2014 Nomor 45, Tambahan Lembaran Negara Republik Indonesia Nomor 5512); 5. Undang -Undang Nomor 23 Tahun 2014 tentang Pemerintahan Daerah (Lembaran Negara Republik Indonesia Tahun 2014 Nom or 244, Tambahan Lembaran Negara Republik Indonesia Nomor 5587) sebagaimana telah beberapa kali diubah, terakhir dengan Undang - Undang Nomor 9 Tahun 2015 tentang Perubahan Kedua atas Undang -Undang Nomor 23 Tahun 2014 tentang Pemerintahan Daerah (Lembaran Ne gara Republik Indonesia Tahun 2015 Nomor 58, Tambahan Lembaran Negara Republik Indonesia Nomor 5679); 6. Undang -Undang Nomor 12 Tahun 201 8 tentang Anggaran Pendapatan dan Belanja Negara Tahun Anggaran 201 9 (Lembaran Negara Republik Indonesia Tahun 2018 Nomor 223, Tambahan Lembaran Negara Republik Indonesia Nomor 6263); 7. Peraturan Pemerintah Nomor 38 Tahun 2007 tentang Pembagian Urusan Pemerintahan antara Pemerintah, Pemerintahan Daerah Provinsi, dan Pemerintahan Daerah Kabupaten/Kota (Lembaran Negara Republik Indonesia Tahun 2007 Nomor 82, Tambahan Lembaran Negara Republik Indonesia Nomor 4737); 8. Peraturan Pemerintah Nomor 7 Tahun 2008 tentang Dekonsentrasi dan Tugas Pembantuan (Lembaran Negara Republik Indonesia Tahun 2008 Nomor 20, Tambahan Lemba ran Negara Republik Indonesia Nomor 4816); 9. Peraturan Pemerintah Nomor 27 Tahun 2014 tentang Pengelolaan Barang Milik Negara/Daerah (Lembaran Negara Republik lndonesia Tahun 2014 Nomor 92, www.peraturan.go.id 2019 , No.178 -3- Tambahan Lembaran Negara Republik lndonesia Nomor 5533) ; 10. Peraturan Pemerintah Nomor 18 Tahun 2016 tentang Perangkat Daerah (Lembaran Negara Republik Indonesia Tahun 2016 Nomor 114, Tambahan Lembaran Negara Republik Indonesia Nomor 5887); 11. Peraturan Presiden Nomor 48 Tahun 2015 tentang Kementerian Perdaganga n (Lembaran Negara Republik Indonesia Tahun 2015 Nomor 90); 12. Peraturan Presiden Nomor 16 Tahun 201 8 tentang Pengadaan Barang/Jasa Pemerintah sebagaimana telah beberapa kali diubah, terakhir dengan Peraturan Presiden Nomor 4 Tahun 2015 tentang Perubaha n Keempat atas Peraturan Presiden",
      "metadata": {
        "page_start": 1,
        "page_end": 1
      }
    },
    {
      "text": "4 Tahun 2015 tentang Perubaha n Keempat atas Peraturan Presiden Nomor 54 Tahun 2010 tentang Pengadaan Barang/Jasa Pemerintah (Lembaran Negara Republik Indonesia Tahun 2015 Nomor 5, Tambahan Lembaran Negara Republik Indonesia Nomor 5655); 13. Peraturan Presiden Nomor 72 Tahun 2018 tentang Rencana Kerja Pemerintah Tahun 201 9 (Lembaran Negara Republik Indonesia Tahun 2018 Nomor 148); 14. Peraturan Menteri Keuangan Nomor 156/PMK.07/2008 tentang Pedoman Pengelolaan Dana Dekonsentrasi dan Dana Tugas Pembantuan sebagaimana telah diubah dengan Peraturan Menteri Keuangan Nomor 248/PMK.07/2010 tentang Perubahan atas Peraturan Menteri Keuangan Nomor 156/PMK.07/2008 tentang Pedoman Pengelolaan Dana Dekonsentrasi dan Tugas Pembantuan (Berita Negara Republik Indonesia Tahun 2010 Nomor 660); 15. Peraturan Menteri Perdagangan Nomor 27/M - DAG/PER/4/2015 tentang Rencana Strategis Kementerian Perdagangan Tahun 2015 – 2019 (Berita Negara Republik Indonesia Tahun 2015 Nomor 575) sebagaimana telah diubah dengan Peraturan Menteri Perdagangan Nomor 81/M-DAG/PER/ 11/201 6 tentang Perubahan atas Peraturan Menteri Perdagangan Nomor www.peraturan.go.id 2019, No.178 -4- 27/M -DAG/PER/4/2015 tentang Rencana Strategis Kementerian Perdagangan Tahun 2015 -2019 (Berita Negara Republik Indonesia Tahun 2016 Nomor 1835); 16. Peraturan Menteri Perdagangan Nomo r 08/M - DAG/PER/2/2016 tentang Organisasi dan Tata Kerja Kementerian Perdagangan (Berita Negara Republik Indonesia Tahun 2016 Nomor 202); MEMUTUSKAN: Menetapkan : PERATURAN MENTERI PERDAGANGAN TENTANG PELIMPAHAN SEBAGIAN URUSAN PEMERINTAHAN DI BIDANG PERDA GANGAN KEPADA GUBERNUR SEBAGAI WAKIL PEMERINTAH PUSAT DALAM RANGKA PENYELENGGARAAN DEKONSENTRASI TAHUN ANGGARAN 2019. BAB I KETENTUAN UMUM Pasal 1 Dalam Peraturan Menteri ini yang dimaksud dengan: 1. Dekonsentrasi adalah pelimpahan sebagian urusan pemeri ntahan yang menjadi kewenangan pemerintah pusat kepada gubernur sebagai wakil pemerintah pusat, kepada instansi vertikal di wilayah tertentu, dan/atau kepada gubernur dan bupati/wali kota sebagai penanggung jawab urusan pemerintahan umum. 2. Dana Dekonsent rasi adalah dana yang berasal dari anggaran pendapatan dan belanja negara yang dilaksanakan oleh gubernur sebagai wakil pemerintah pusat yang mencakup semua penerimaan dan pengeluaran dalam rangka pelaksanaan Dekonsentrasi, tidak termasuk dana yang akan di alokasikan untuk instansi vertikal pusat di daerah. 3. Anggaran Pendapatan dan Belanja Negara yang selanjutnya disingkat APBN adalah rencana keuangan tahunan pemerintahan negara yang disetujui oleh Dewan Perwakilan Rakyat. www.peraturan.go.id 2019 , No.178 -5- 4. Anggaran Pendapatan dan Belan ja Daerah yang selanjutnya disingkat APBD adalah rencana keuangan tahunan pemerintah daerah yang disetujui Dewan Perwakilan Rakyat Daerah dan ditetapkan dengan Peraturan Daerah. 5. Rencana Kerja Kementerian/Lembaga yang selanjutnya disebut Renja -K/L adalah dokumen perencanaan kementerian/lembaga untuk periode 1 (satu) tahun. 6. Rencana Kerja dan Anggaran Kementerian/Lembaga yang selanjutnya disingkat RKA -K/L adalah dokumen perencanaan dan penganggaran yang berisi program dan kegiatan suatu kementerian/lemba ga yang merupakan penjabaran dari rencana kerja pemerintah dan rencana strategis kementerian/lembaga yang bersangkutan dalam 1 (satu) tahun anggaran, serta anggaran yang diperlukan untuk melaksanakannya. 7. Kegiatan yang bersifat non -fisik adalah kegiatan yang menghasilkan keluaran yang tidak menambah aset tetap, antara lain berupa sinkronisasi dan koordinasi perencanaan, fasilitasi, bimbingan teknis, pelatihan, penyuluhan, supervisi, penelitian dan survey, pembinaan dan pengawasan, serta pengendalian. 8. Barang Milik Negara yang selanjutnya disingkat BMN adalah semua barang yang dibeli atau diperoleh atas beban APBN atau berasal dari perolehan lainnya yang sah. 9. Perangkat",
      "metadata": {
        "page_start": 1,
        "page_end": 1
      }
    },
    {
      "text": "APBN atau berasal dari perolehan lainnya yang sah. 9. Perangkat Daerah Provinsi yang selanjutnya disingkat PD Provinsi adalah organisasi/lembaga pad a pemerintah daerah yang bertanggung jawab terhadap pelaksanaan dekonsentrasi/tugas pemerintahan di bidang perdagangan di daerah provinsi. 10. Menteri adalah menteri yang menyelenggarakan urusan pemerintahan di bidang perdagangan. www.peraturan.go.id 2019, No.178 -6- BAB II TUJUAN Pasal 2 Peraturan Menteri ini bertujuan untuk memberikan arah kebijakan Pemerintah di bidang perdagangan kepada Gubernur sebagai wakil Pemerintah untuk melaksanakan dan meng koordinasikan penyelenggaraan Dekonsentrasi di bidang perdagangan di daerah. BAB III LING KUP URUSAN YANG DILIMPAHKAN Pasal 3 (1) Pemerintah melimpahkan sebagian urusan pemerintahan di bidang perdagangan yang menjadi kewenangan Menteri kepada gubernur sebagai wakil pemerintah. (2) Sebagian urusan pemerintahan di bidang perdagangan yang dilimpa hkan kepada gubernur merupakan kegiatan yang bersifat non -fisik sebagaimana dimaksud pada ayat (1) tercantum dalam Lampiran yang merupakan bagian tidak terpisahkan dari Peraturan Menteri ini. (3) Sebagian urusan pemerintahan sebagaimana dimaksud pada ayat (2) telah ditetapkan dalam Renja K/L yang mengacu pada rencana kerja pemerintah dan RKA -K/L Tahun Anggaran 201 9. BAB IV PENYELENGGARAAN DEKONSENTRASI Pasal 4 (1) Menteri melimpahkan sebagian urusan pemerintahan di bidang perdagangan kepada 34 (tiga puluh empat) gubernur. (2) Pelimpahan sebagian urusan pemerintahan di bidang perdagangan sebagaimana dimaksud dalam Pasal 3 ayat (2) tidak dapat dilimpahkan kepada pihak lain. www.peraturan.go.id 2019 , No.178 -7- (3) Pelimpahan sebagian urusan pemerintahan di bidang perdagangan sebagaimana dimaks ud pada ayat (1), berlaku sampai dengan tanggal 31 Desember 201 9. Pasal 5 (1) Dalam penyelenggaraan sebagian urusan pemerintahan di bidang perdagangan sebagaimana dimaksud dalam Pasal 3 ayat (3), gubernur harus: a. melakukan sinkronisasi terhadap penyelen ggaraan urusan pemerintahan daerah dan menjamin kegiatan Dekonsentrasi dilaksanakan secara efektif dan efisien; dan b. menjamin terwujudnya koordinasi, pengendalian, pembinaan, pengawasan, dan pelaporan. (2) Gubernur memberitahukan kepada Dewan Perwakilan Rakyat Daerah berkaitan dengan penyelenggaraan sebagian urusan pemerintahan sebagaimana dimaksud dalam Pasal 3 ayat (3). (3) Penyelenggaraan urusan pemerintahan yang dilimpahkan kepada Gubernur sebagaimana dimaksud dalam Pasal 3 ayat (2) berpedoman pada no rma, standar, prosedur, kriteria, dan kebijakan Pemerintah serta keserasian, kemanfaatan, dan kelancaran pelaksanaan tugas pemerintahan dan pembangunan daerah. Pasal 6 (1) Gubernur menetapkan PD Provinsi yang bertanggung jawab di bidang perdagangan sebaga i pelaksana urusan pemerintahan di bidang perdagangan. (2) Gubernur menetapkan pejabat pengelola keuangan yang terdiri atas: a. kuasa pengguna anggaran/barang yang dijabat oleh Kepala PD Provinsi; b. pejabat pembuat komitmen; c. pejabat penguji tagihan/pen andatangan surat perintah membayar; dan d. pejabat akuntasi dan bendahara pengeluaran. www.peraturan.go.id 2019, No.178 -8- (3) Gubernur menyampaikan hasil penetapan sebagaimana dimaksud pada ayat (2) kepada Menteri dengan tembusan menteri yang menyelenggarakan urusan pemerintahan di bidang k euangan melalui direktur jenderal yang tugas dan tanggung jawabnya di bidang perbendaharaan. (4) PD Provinsi sebagaimana dimaksud pada ayat (1), melaksanakan anggaran dengan berpedoman pada norma, standar, prosedur, dan kriteria yang ditetapkan oleh Menter i dan ketentuan peraturan perundang - undangan. (5) Gubernur melakukan koordinasi dengan Menteri mengenai: a. pelaksanaan fungsi pengaturan, pembinaan, dan pengawasan teknis atas pelaksanaan kegiatan Dekonsentrasi; dan b. pelaksanaan pemantauan dan evaluasi terhadap",
      "metadata": {
        "page_start": 1,
        "page_end": 2
      }
    },
    {
      "text": "pelaksanaan kegiatan Dekonsentrasi; dan b. pelaksanaan pemantauan dan evaluasi terhadap capaian pelaksanaan teknis di daerah yang dilakukan oleh PD Provinsi yang bertanggung jawab di bidang perdagangan. (6) Koordinasi sebagaimana dimaksud pada ayat (5) dilakukan melalui: a. direktur jenderal perdagangan dalam negeri; b. direktur jen deral perlindungan konsumen dan tertib niaga; c. direktur jenderal perdagangan luar negeri; d. direktur jenderal perundingan perdagangan internasional; e. direktur jenderal pengembangan ekspor nasional; f. kepala badan pengawas perdagangan berjangka omodi ti; dan g. inspektur jenderal. Pasal 7 PD Provinsi dilarang melakukan revisi daftar isian pelaksanaan anggaran yang mengakibatkan perubahan output kegiatan, termasuk perubahan pagu antar program dan pagu antar kegiatan. www.peraturan.go.id 2019 , No.178 -9- BAB V TUGAS DAN TANGGUNG JAWAB PELAKSANAAN KEGIATAN Pasal 8 (1) Kepala PD Provinsi bertugas dan bertanggung jawab atas pelaksanaan kegiatan Dekonsentrasi. (2) Tugas dan tanggung jawab pelaksanaan kegiatan sebagaimana dimaksud pada ayat (1) berpedoman pada norma, standar, prosedur, dan kr iteria yang ditetapkan Menteri dan gubernur sebagai wakil pemerintah. BAB VI PENDANAAN Pasal 9 (1) Sebagian urusan pemerintahan sebagaimana dimaksud dalam Pasal 3 ayat (2) pendanaannya dibebankan pada APBN pada bagian anggaran Kementerian Perdagangan Tahun Anggaran 201 9 melalui Dana Dekonsentrasi bidang perdagangan. (2) Rincian alokasi anggaran Dekonsentrasi Tahun Anggaran 2019 untuk masing -masing kegiatan Dekonsentrasi di bidang perdagangan sebagaimana tercantum dalam Lampiran yang merupakan bagian tidak terpisahkan dari Peraturan Menteri ini. (3) Penyaluran Dana Dekonsentrasi dilakukan oleh bendahara umum negara atau kuasanya melalui rekening kas umum negara di daerah. (4) Tata cara penyaluran Dana Dekonsentrasi dilaksanakan sesuai dengan ketentuan perat uran perundang - undangan. www.peraturan.go.id 2019, No.178 -10- BAB VII PENGELOLAAN BMN HASIL PELAKSANAAN DEKONSENTRASI Pasal 10 (1) Pengadaan barang yang diperoleh dari pelaksanaan Dana Dekonsentrasi merupakan BMN. (2) BMN sebagaimana dimaksud pada ayat (1) digunakan sebagai penunjang p elaksanaan kegiatan Dekonsentrasi. (3) PD Provinsi melakukan penatausahaan BMN sebagaimana dimaksud pada ayat (1) sesuai dengan ketentuan Peraturan Menteri Keuangan yang mengatur mengenai penatausahaan BMN. (4) BMN sebagaimana dimaksud pada ayat (1) dapat dihibahkan kepada daerah. (5) Dalam hal BMN dihibahkan kepada daerah, penatausahaan, penggunaan, dan pemanfaatan BMN tersebut dilaksanakan oleh pemerintah provinsi sebagai barang milik daerah. (6) Penghibahan, penatausahaan, penggunaan, dan pemanfaatan bar ang sebagaimana dimaksud pada ayat (5) merupakan bagian yang tidak terpisahkan dari pengelolaan BMN atau barang milik daerah. (7) Tata cara pengelolaan BMN serta pengendalian dan pengawasannya dilaksanakan sesuai dengan ketentuan Peraturan Menteri Keuangan yang mengatur mengenai tata cara pelaksanaan penggunaan, pemanfaatan, penghapusan, dan pemindahtanganan BMN. BAB VIII LAPORAN PERTANGGUNGJAWABAN Pasal 11 (1) Kepala PD Provinsi berkewajiban menyusun laporan pertanggungjawaban yang meliputi laporan manaj erial dan laporan akuntabilitas. (2) Laporan manajerial sebagaimana dimaksud pada ayat (1) meliputi: www.peraturan.go.id 2019 , No.178 -11- a. perkembangan realisasi penyerapan anggaran; b. pencapaian target keluaran; c. kendala yang dihadapi; dan d. saran tindak lanjut. (3) Laporan akuntabilit as sebagaimana dimaksud pada ayat (1) meliputi laporan keuangan dan laporan barang. (4) Laporan keuangan sebagaimana dimaksud pada ayat (3) terdiri atas: a. neraca; b. laporan realisasi anggaran; dan c. catatan atas laporan keuangan. Pasal 12 (1) Kepala PD Provinsi menyampaikan laporan",
      "metadata": {
        "page_start": 2,
        "page_end": 2
      }
    },
    {
      "text": "laporan keuangan. Pasal 12 (1) Kepala PD Provinsi menyampaikan laporan manajerial sebagaimana dimaksud dalam Pasal 11 ayat (2) kepada Menteri melalui aplikasi e -Monitoring Kementerian Perdagang an setiap pencairan anggaran. (2) Kepala PD Provinsi menyampaikan laporan akuntabilitas sebagaimana di maksud dalam Pasal 11 ayat (3) kepada Menteri melalui Sekretaris Jenderal Kementerian Perdagangan, berupa: a. laporan keuangan; dan b. laporan BMN . (3) Laporan akuntabilitas sebagaimana dimaksud pada ayat (2) disampaikan setiap triwulan dan akhir tahun anggaran sesuai Standar Akuntansi Pemerintah. Pasal 13 Penatausahaan keuangan dan BMN dalam pelaksanaan Dekonsentrasi dilakukan secara terpisah dari penatausahaan keuangan dan BMN dalam pelaksanaan Tugas Pembantuan APBN dan APBD. Pasal 14 (1) Tata cara peny usunan dan penyampaian laporan manajerial sebagaimana dimaksud dalam Pasal 11 ayat (2) berpedoman pada ketentuan peraturan perundang - www.peraturan.go.id 2019, No.178 -12- undangan yang mengatur mengenai tata cara pengendalian dan evaluasi pelaksanaan rencana pembangunan. (2) Tata cara penyusun an laporan keuangan sebagaimana dimaksud dalam Pasal 11 ayat (4) berpedoman pada ketentuan Peraturan Menteri Keuangan yang mengatur mengenai sistem akuntansi dan pelaporan keuangan pemerintah. (3) Tata cara penyusunan laporan barang sebagaimana dimaksud da lam Pasal 11 ayat (3) berpedoman pada ketentuan Peraturan Menteri Keuangan yang mengatur mengenai penatausahaan BMN. BAB IX PEMBINAAN DAN PENGAWASAN Pasal 15 (1) Menteri melakukan pembinaan dan pengawasan dalam penyelenggaraan sebagian urusan pemerintaha n yang dilimpahkan kepada Gubernur. (2) Gubernur selaku penerima pelimpahan sebagian urusan pemerintahan dari Pemerintah melakukan pembinaan dan pengawasan terhadap kegiatan Dekonsentrasi di bidang perdagangan yang dilaksanakan oleh PD Provinsi. (3) Pembin aan sebagaimana dimaksud pada ayat (1) meliputi pemberian pedoman, fasilitasi, pelatihan, bimbingan teknis, pemantauan, dan evaluasi. (4) Pembinaan sebagaimana dimaksud pada ayat (1) dan ayat (3) dilaksanakan oleh: a. sekretaris jenderal; b. direktur jend eral perdagangan dalam negeri; c. direktur jenderal perlindungan konsumen dan tertib niaga; d. direktur jenderal perdagangan luar negeri; e. direktur jenderal perundingan perdagangan internasional; f. direktur jenderal pengembangan ekspor nasional; dan www.peraturan.go.id 2019 , No.178 -13- g. kepala badan pengawas perdagangan berjangka komoditi. (5) Norma, standar, prosedur, dan kriteria sebagaimana dimaksud dalam Pasal 5 ayat (3) merupakan instrumen pembinaan untuk melaksanakan urusan pemerintahan di bidang perdagangan yang dilimpahkan kepad a gubernur. (6) Pengawasan fungsional terhadap pelaksanaan kegiatan Dekonsentrasi, dan pemeriksaan atas laporan keuangan Dana Dekonsentrasi sebagaimana dimaksud dalam Pasal 11 ayat (4) dilaksanakan oleh inspektorat jenderal . BAB X PENARIKAN KEMBALI PELIMP AHAN Pasal 16 (1) Menteri dapat menarik kembali urusan pemerintahan di bidang perdagangan yang dilimpahkan kepada gubernur, jika: a. Menteri mengubah kebijakan; b. gubernur dalam melaksanakan sebagian urusan pemerintahan sebagaimana dimaksud dalam Pasal 3 ayat (3) tidak sesuai dengan norma, standar, prosedur, dan kriteria yang ditetapkan oleh Menteri atau ketentuan peraturan perundang -undangan; dan/atau c. gubernur mengusulkan untuk ditarik kembali sebagian atau seluruhnya urusan pemerintahan di bidang per dagangan yang dilimpahkan kepada gubernur. (2) Penarikan kembali urusan pemerintahan bidang perdagangan sebagaimana dimaksud pada ayat (1), ditetapkan dengan Peraturan Menteri. (3) Peraturan Menteri sebagaimana dimaksud pada ayat (2) digunakan oleh menteri yang menyelenggaraan urusan pemerintahan di bidang keuangan sebagai dasar pemblokiran dalam dokumen anggaran dan penghentian www.peraturan.go.id",
      "metadata": {
        "page_start": 2,
        "page_end": 2
      }
    },
    {
      "text": "keuangan sebagai dasar pemblokiran dalam dokumen anggaran dan penghentian www.peraturan.go.id 2019, No.178 -14- pencairan Dana Dekonsentrasi. BAB XI SANKSI Pasal 17 (1) PD Provinsi yang melanggar ketentuan sebagaimana dimaksud dalam Pasal 7 , Pasal 11, dan Pasal 12 dikenakan sanksi berupa penghentian alokasi pendanaan untuk tahun anggaran berikutnya. (2) Dalam hal ditemukan adanya penyimpangan dari hasil pemeriksaan sebagaimana dimaksud dalam Pasal 15 ayat (6), PD Provinsi dikenakan sanksi be rupa penghentian alokasi pendanaan untuk tahun anggaran berikutnya. (3) Sanksi penghentian alokasi pendanaan sebagaimana dimaksud pada ayat (1) dan ayat (2) ditetapkan oleh Menteri setelah berkonsultasi dengan menteri yang menyelenggaraan urusan pemerintah an di bidang keuangan. BAB XII KETENTUAN LAIN -LAIN Pasal 18 Ketentuan lebih lanjut mengenai petunjuk teknis pelaksanaan kegiatan Dekonsentrasi di bidang perdagangan diatur dengan Peraturan Menteri. BAB XIII PENUTUP Pasal 19 Peraturan Menteri ini mulai berlaku pada tanggal 1 Januari 2019. www.peraturan.go.id 2019 , No.178 -15- Agar setiap orang mengetahuinya, memerintahkan pengundangan Peraturan Menteri ini dengan penempatannya dalam Berita Negara Republik Indonesia. Ditetapkan di Jakarta pada tanggal 11 Februari 2019 MENTERI PERDAGANGAN REPUBLIK INDONESIA, ttd ENGGARTIASTO LUKITA Diundangkan di Jakarta pada tanggal 21 Februari 2019 DIREKTUR JENDERAL PERATURAN PERUNDANG -UNDANGAN KEMENTERIAN HUKUM DAN HAK ASASI MANUSIA REPUBLIK INDONESIA, ttd WIDODO EKATJAHJANA www.peraturan.go.id 2019, No.178 -16- www.peraturan.go.id 2019 , No.178 -17- www.peraturan.go.id 2019, No.178 -18- www.peraturan.go.id 2019 , No.178 -19- www.peraturan.go.id 2019, No.178 -20- www.peraturan.go.id 2019 , No.178 -21- www.peraturan.go.id 2019, No.178 -22- www.peraturan.go.id",
      "metadata": {
        "page_start": 2,
        "page_end": 2
      }
    }
  ]
}