{
  "source": "downloaded_pdfs/bn263-2013lamp.pdf",
  "processed_date": "2025-04-24T17:10:14.301619",
  "document_info": {
    "title": "BN 263-2013.doc"
  },
  "total_pages": 5,
  "chunks": [
    {
      "text": "2013, No.263 9 KEKUATAN PRAJURIT TENTARA NASIONAL INDONESIA PER PA NGKAT PER UNIT ORGANISASI TRIWULAN:….. TA ….. KONDISI PER …..20….. MABES TNI TNI AD TNI AL TNI AU DI LUAR STRUKTUR NO PANGKAT PRIA WANITA JUMLAH PRIA WANITA JUMLAH PRIA WANITA JUMLAH PRIA WANITA JUMLAH PRIA WANITA JUMLAH 1 2 3 4 5 6 7 8 9 10 11 12 13 14 15 16 17 JUMLAH KA SATKER _______________ MENTERI PERTAHANAN REPUBLIK INDONESIA , PURNOMO YUSGIANTORO LAMPIRAN I PERATURAN MENTE RI PERTAHANAN REPUBIK INDONESIA NOMOR 02 TAHUN 2013 TENTANG SISTEM PELAPORAN KEKUATAN PERSONEL KEMENTERIAN PERTAHANAN DAN TENTARA NASIONAL INDONESIA KOP www.djpp.kemenkumham.go.id 2013, No.263 10 LAMPIRAN I I PERATURAN MENTE RI PERTAHANAN REPUBIK INDONESIA NOMOR 02 TAHUN 2013 TENTANG SISTEM PELAPORAN KEKUATAN PERSONEL KEMENTERIAN PERTAHANAN DAN TENTARA NASIONAL INDONESIA REKAPITULASI KEKUATAN PRAJURIT TENTARA NASIONAL INDONESIA DAN KELUARGA PER PAN GKAT PER UNIT PER MARKAS BESAR TENTARA NASIONAL INDONESIA/LUAR STRUKTUR TENTARA NASIONAL INDONESIA TRIWULAN:….. TA ….. KONDISI PER …..20….. TNI AD TNI AL TNI AU JUMLAH NO PANGKAT PRIA WANITA JUMLAH PRIA WANITA JUMLAH PRIA WANITA JUMLAH PRIA WANITA JUMLAH ISTRI SUAMI JML ANAK YG DAPAT TUNJAN GAN 1 2 3 4 5 6 7 8 9 10 11 12 13 14 15 16 17 18 JUMLAH KA SATKER _______________ MENTERI PERTAHANAN REPUBLIK INDONESIA , PURNOMO YUSGIANTORO KOP www.djpp.kemenkumham.go.id 2013, No.263 11 LAMPIRAN I II PERATURAN MENTE RI PERTAHANAN REPUBIK INDONESIA NOMOR 02 TAHUN 2013 TENTANG SISTEM PELAPORAN KEKUATAN PERSONEL KEMENTERIAN PERTAHANAN DAN TENTARA NASIONAL INDONESIA KOP REKAPITULASI KEKUATAN PEGAWAI NEGERI SIPIL KEMENTERIAN PERTAHAN AN DAN KELUARGA PER GOLONGAN RUANG PER UNIT ORGANISASI TRIWULAN:….. TA … .. KONDISI …..20….. MABES TNI TNI AD TNI AL TNI AU DI LUAR STRUKTUR NO GOL RUANG PRIA WANITA JML PRIA WANITA JML PRIA WANITA JML PRIA WANITA JML PRIA WANITA JML ISTRI SUAMI JML ANAK YG DAPAT TUNJANGAN JML KET 1 2 3 4 5 6 7 8 9 10 11 12 13 14 15 16 17 18 19 20 21 22 23 JUMLAH KA SATKER _______________ MENTERI PERTAHANAN REPUBLIK INDONESIA , PURNOMO YUSGIANTORO www.djpp.kemenkumham.go.id 2013, No.263 12 LAMPIRAN I V PERATURAN MENTE RI PERTAHANAN REPUBIK INDONESIA NOMOR 02 TAHUN 2013 TENTANG SISTEM PELAPORAN KEKUATAN PERSONEL KEMENTERIAN PERTAHANAN DAN TENTARA NASIONAL INDONESIA REKAPITULASI KEKUATAN PEGAWAI NEGERI SIPIL TENTARA NASIONAL INDONESIA PER GOLONGAN RUANG PER ANGKATAN TRIWULAN:….. TA … .. KONDISI …..20….. NYATA NO GOLONGAN RUANG DST/TOP PRIA WANITA JUMLAH ISTRI SUAMI JUMLAH JUMLAH ANAK YANG DAPAT TUNJANGAN JUMLAH 1 2 3 4 5 6 7 8 9 10 11 JUMLAH KA SATKER _______________ MENTERI PERTAHANAN REPUBLIK INDONESIA , PURNOMO YUSGIANTORO www.djpp.kemenkumham.go.id 2013, No.263 13 LAMPIRAN V PERATURAN MENTE RI PERTAHANAN REPUBIK INDONESIA NOMOR 02 TAHUN 2013 TENTANG SISTEM PELAPORAN KEKUATAN PERSONEL KEMENTERIAN PERTAHANAN DAN TENTARA NASIONAL INDONESIA REKAPITULASI KEKUAT AN PEGAWAI NEGERI SIPIL TENTARA NASIONAL INDONESIA PER KATEGORI PER UNIT ORGANISASI TRIWULAN:….. TA ….. KONDISI …..20….. MABES TNI TNI AD TNI AL TNI AU Jumlah Besar NO KATEGORI PRIA WANITA JML PRIA WANITA JML PRIA WANITA JML PRIA WANITA JML PRIA WANITA JML KET 1",
      "metadata": {
        "page_start": 1,
        "page_end": 1
      }
    },
    {
      "text": "WANITA JML PRIA WANITA JML PRIA WANITA JML KET 1 2 3 4 5 6 7 8 9 10 11 12 13 14 15 16 17 18 1. Aktif Organisasi Satuan a. PNS b. CPNS 2. Non Aktif Organik Satuan a Bebas Tugas b Dipekerjakan c Diperbantukan d Luar Formasi e Sbg Pjb Neg f f. Skorsing JUMLAH KA SATKER ______________ MENTERI PERTAHANAN REPUBLIK INDONESIA , PURNOMO YUSGIANTORO KOP www.djpp.kemenkumham.go.id",
      "metadata": {
        "page_start": 1,
        "page_end": 1
      }
    }
  ]
}