{
  "source": "downloaded_pdfs/PP%20Nomor%2030%20Tahun%202021.pdf",
  "processed_date": "2025-04-12T21:24:06.597459",
  "document_info": {
    "title": null
  },
  "total_pages": 57,
  "chunks": [
    {
      "text": "SALINAN PRESIDEN REPUBLIK INDONESIA PERATURAN PEMERINTAH REPUBLIK INDONESIA NOMOR 30 TAHUN 2O2L TENTANG PEI{YELENGGARAAN BIDANG LALU LINTAS DAN ANGKUTAN JALAN DENGAN RAHMAT TUHAN YANG MAHA ESA PRESIDEN REPUBLIK INDONESIA, bahwa untuk melaksanakan ketentuan Pasal 55 dan Pasal 185 huruf b Undang-Undang Nomor 11 Tahun 2O2A tentang Cipta Kerja, perlu menetapkan Peraturan Pemerintah tentang Penyelenggaraan Bidang Lalu Lintas dan Angkutan Jalan;Menimbang Mengingat Menetapkan1 2 3Pasal 5 ayat (2) Undang-Undang Dasar Negara Republik Indonesia Tahun 7945; Undang-Undang Nomor 22 Tahun 2OO9 tentang Lalu Lintas dan Angkutan Jalan (Lembaran Negara Republik Indonesia Tahun 2OO9 Nomor 96, Tambahan Lembaran Negara Republik Indonesia Nomor 5025); Undang-Undang Nomor 11 Tahun 2020 tentang Cipta Kerja (Lembaran Negara Republik Indonesia Tahun 2O2O Nomor 245, Tambahan kmbaran Negara Republik Indonesia Nomor 6573l'1, MEMUTUSKAN: PERATURAN PEME RI NTAH TENTANG PENYELENGGARAAN BIDANG LALU LTNTAS DAN ANGKUTAN JALAN. SK No 085099ABAB I PRES lDEN REPUBLIK tNDONESiA -2- BAB I KETENTUAN UMUM Pasal 1 Dalam Peraturan Pemerintah ini yang dimaksud dengan: 1. Lalu Lintas dan Angkutan Jalan adalah satu kesatuan sistem yang terdiri atas lalu lintas, angkutan jalan, jaringan lalu lintas dan angkutan jalan, prasarana lalu lintas dan angkutan jalan, kendaraan, penglemudi, pengguna jalan, serta pengelolaannya. 2. Lalu Lintas adalah gerak kendaraan dan orang di rLlang lalu lintas jalan. 3. Prasarana Lalu Lintas dan Angkutan Jalan adalah ruang lalu lintas, terminal, dan perlengkapan jalan yang meliputi marka, rambu, alat pemberi isyarat lalu lintas, alat pengendali dan pengarnan pengguna jalatt, alat pengawasan dan pengamanan jalan, serta fasilitas pendukung. 4. Kendaraan adalah suatu sarana angkut di jalan yang terdiri atas kendaraan bermotor dan kendaraan tidak bermotor. 5. Kendaraan Bermotor adalah setiap Kendaraan yang digerakkan oleh peralatan mekanik berupa mesin selain Kendaraan yang berjalan di atas rel. 6. Jalan adalah seluruh bagian jalan, termasuk bangunan pelengkap dan perlengkapannya yang diperuntukkan bagi Lalu Lintas umum, yang berada pada permukaan tanah, di atas permukaan tanah, di bawah permukaan tanah dan/atau air, serta di atas permukaan air, kecuali jalan rel dan jalan kabel. 7. Terminal adalah pangkalan Kendaraan Bermotor umum yang digunakan untuk mengatur kedatangan dan keberangkatan, menaikkan dan menurunkan orang danf atau barang, serta perpindahan moda angkutan. 8.Parkir... SK No 093127 A PRES IDEN REPUBLIK INDONESIA -3- 8. Parkir acla-lah keadaan Kendaraan berhenti atau tidak bergerak untuk beberapa saat dan ditinggalkan pengemudinya. 9. Rambu Lalu Lintas adalah bagian perlengkapan Jalan yang berupa lambang, huruf, angka, kalimat, dan/atau perpaduan yang berfungsi sebagai peringatan, larangan, perintah, atau petunjuk bagi pengguna Jalan. 10. Marka Jalan adalah suatu tanda yang berada di permukaan Jalan atau di atas permukaan Jalan yang meliputi peralatan atau tanda yang membentuk garis membujur, garis melintang, garis serong, serta lambang yang berfungsi untuk mengarahkan arus Lalu Lintas dan membatasi daerah kepentingan Lalu Lintas. 1 1. Alat Pemberi Isyarat Lalu Lintas adalah perangkat elektronik yang menggunakan isyarat lampu yang dapat dilengkapi dengan isyarat bunyi untuk mengatur Lalu Lintas orang dan/atau Kendaraan di persimpangan atau pada ruas Ja-lan. 12. Perizinan Berusaha ada-lah legalitas yang diberikan kepada pelaku usaha untuk memulai dan menjalankan usah a dan I atau kegiatannya. 13. Perusahaan",
      "metadata": {
        "page_start": 1,
        "page_end": 1
      }
    },
    {
      "text": "dan menjalankan usah a dan I atau kegiatannya. 13. Perusahaan Angkutan Umum adalah bad.an hukum yang menyediakan jasa angkutan orang dan/atau barang dengan Kendaraan Bermotor umum. 14. Pengemudi adalah orang yang mengemudikan Kendaraan Bermotor di Ja-lan yang telah memiliki Surat Izin Mengemudi. 15. Penumpang adalah orang yang berada di Kendaraan seiain Pengemudi dan awak Kendaraan. 16. Pengguna Jalan adalah orang yang menggunakan Jalan untuk berlalu lintas. 17. Kelancaran Lalu Lintas dan Angkutan Jalan adalah suatu keadaan berla-lu lintas dan penggunaan angkutan yang bebas dari hambatan dan kemacetan di Jalan' 1g. Sertif,rkat . . . SK No 093128 A PRES IDEN REPUBLIK INDONESIA -4- 18. Sertifikat Kompetensi adalah tanda bukti seseorang telah memenuhi persyaratan pengetahuan, keahlian, dan kualifikasi di bidangnya. 79. Pemerintah Pusat adalah Presiden Republik Indonesia yang memegang kekuasaan pemerintahan negara Republik Indonesia yang dibantu oleh Wakil Presidendan menteri sebagaimana dimaksud dalam Undang-Undang Dasar Negara Republik Indonesia Tahun 1945. 20. Pemerintah Daerah ada-lah kepala daerah sebagaiunsur penyelenggara pemerintahan daerah yang memimpin pelaksanaan urusan pemerintahan yang menjadi kewenangan daerah otonom. 21. Kementerian adalah kementerian yang menyelenggarakan urusan pemerintahan di bidang sa-rana dan Prasarana Lalu Lintas dan Angkutan Jalan. 22. Menteri ada-lah menteri yang menyelenggarakan urusan pemerintahan di bidang sarana dan Prasarana Lalu Lintas dan Angkutan Jalan. BAB II ANALISIS DAMPAK LALU LINTAS Pasal 2 (1) Setiap rencana pembangunan pusat kegiatan,permukiman, dan infrastruktur yang akan menimbulkan gangguan keamanan, keselamatan, ketertiban, dan Kelancaran Lalu Lintas dan Angkutan Jalan wajib dilakukan analisis dampak Lalu Lintas. (2) Dokumen analisis dampak Lalu Lintas terintegrasidengan dokumen analisis mengenai dampak lingkungan hidup atau upaya pengelolaan lingkungan hidup dan upaya pemantauan lingkungan hidup. SK No 093320 APasal 3 PRES IDEN REPUBLIK INDONESTA -5 Pasal 3 (1) Pusat kegiatan sebagaimana dimaksud dalam Pasal 2 ayat (1) berupa bangunan untuk: a. kegiatan perdagangan; b. kegiatanperkantoran; c. kegiatan industri; d. kegiatan pariwisata; e. fasilitas pendidikan; f. fasilitas pelayanan umum; dan/atau g. kegiatan lain yang dapat menimbulkan bangkitan dan/atau tarikan Lalu Lintas. (2) Permukiman sebagaimana dimaksud dalam Pasal 2 ayat (1) berupa: a. perumahan dan permukiman; b. rumah susun dan apartemen; dan/atau c. permukiman lain yang dapat menimbulkan bangkitan dan/atau tarikan Lalu Lintas. (3) Infrastruktur sebagaimana dimaksud dalam Pasal 2 ayat (1) berupa: a. akses kb dan dari Jalan tol; b. pelabuhan; c. bandar udara; d. Terminal; e. stasiun kereta api; f. tempat penyimpanan Kendaraan; g. fasilitas Parkir untuk umum; dan/atau h. infrastruktur lain yang dapat menimbulkan bangkitan dan/atau tarikan Lalu Lintas. SK No 093130 A(4) Pusat... PRES IDEN REPUBLIK INDONESIA -6- (4) Pusat kegiatan, permukiman, dan infrastruktur yangwajib dilakukan analisis dampak Lalu Lintas sebagaimana dimaksud pada ayat (1), ayat (2), dan ayat (3) digolongkan dalam 3 (tiga) kategori skala dampak bangkitan Lalu Lintas yang ditimbulkan sebagai berikut: a. kegiatan dengan bangkitan Lalu Lintas yang tinggi; b. kegiatan dengan bangkitan Lalu Lintas yang. sedangi dan c. kegiatan dengan bangkitan Lalu Lintas yang rendah. (5) Ketentuan lebih lanjut mengenai kategori skala dampak bangkitan Lalu Lintas untuk kegiatan sebagaimana dimaksud pada ayat (4) diatur dengan Peraturan Menteri. Pasal 4 Hasil analisis dampak LaIu Lintas yang",
      "metadata": {
        "page_start": 1,
        "page_end": 1
      }
    },
    {
      "text": "Peraturan Menteri. Pasal 4 Hasil analisis dampak LaIu Lintas yang terintegrasi dengan analisis mengenai dampak lingkungan hidup atau upaya pengelolaan lingkungan hidup dan upaya pemantauan lingkungan hidup sebagaimana dimaksud dalam Pasal 2 dilaksanakan dalam rangka memenuhi Perizinan Berusaha dalam kegiatan pendirian bangunan. Pasa-l 5 (1) Pengembang atau pembangun wajib melaksanakan ana-lisis dampak Lalu Lintas sesuai dengan ska-la dampak bangkitan Lalu Lintas sebagaimana dimaksud dalam Pasal 3 ayat (4) untuk kegiatan yang diajukan oleh pengembang atau pembangun. (2) Analisis dampak Lalu Lintas sebagaimana dimaksud pada ayat (1) dilakukan dengan ketentuan sebagai berikut: SK No 093131 Aa. untuk PRES IDEN REPUBLIK INDONESIA -7 a. untuk kegiatan dengan bangkitan Lalu Lintas yang tinggi, pengembang atau pembangun diwajibkan untuk menyampaikan dokumen analisis dampak Lalu Lintas yang disusun oleh tenaga ahli yang memiliki Sertifikat Kompetensi pen5rusun analisis dampak Lalu Lintas; b. untuk kegiatan dengan bangkitan Lalu Lintas yang sedang, pengembang atau pembangun diwajibkan untuk menyampaikan rekomendasi teknis penanganan dampak Lalu Lintas yang disusun oleh tenaga ahli yang memiliki Sertifikat Kompetensi pen)rusun analisis dampak Lalu Lintas; atau untuk kegiatan dengan bangkitan La-lu Lintas yang rendah, pengembang atau pembangun diwajibkan untuk: 1. memenuhi standar teknis penanganan dampak Lalu Lintas yang telah ditetapkan oleh Menteri; dan 2. menyampaikan gambaran umum lokasi dan rencana pembangunan atau pengembangan yang akan dilaksanakan. (3) Hasil analisis dampak Lalu Lintas sebagaimana dimaksud pada ayat (2) merupakan bagian dokumen analisis dampak Lalu Lintas yang terintegrasi dengan dokumen analisis mengenai dampak lingkungan hidup atau upaya pengelolaan lingkungan hidup dan upaya pemantauan lingkungan hidup. (4) Sertifikat Kompetensi penlrusun analisis dampak Lalu Lintas sebagaimana dimaksud pada ayat (2) huruf a dan huruf b diterbitkan oleh Menteri. (5) Ketentuan lebih lanjut mengenai persyaratan dan tata cara untuk memperoleh Sertifikat Kompetensi pen5rusun analisis dampak LaIu Lintas sebagaimana dimaksud pada ayat (4) diatur dengan Peraturan Menteri. SK No 093132 APasal 6. . PRES IDEN REPUBLIK INDONESIA -8- Pasal 6 (1) Dokumen analisis dampak Lalu Lintas sebagaimana dimaksud dalam Pasal 5 ayat (2) huruf a paling sedikit memuat: a. perencanaan dan metodologi analisis dampak LaJu Lintas; b. analisis kondisi La-lu Lintas dan Angkutan Jalan saat ini; c. analisis bangkitan/tarikan Lalu Lintas dan Angkutan Jalan akibat pembangunan berdasarkan kaidah teknis transportasi dengan menggunakan faktor trip rate yartg ditetapkan secara nasional; d. analisis distribusiperjalanan; e. analisis pemilihan moda; f. analisis pembebanan perjalallan; g. simulasi kinerja Lalu Lintas yang dilakukan terhadap analisis dampak Lalu Lintas; h. rekomendasi dan rencana implementasi penanganan dampak Lalu Lintas; i. rincian tanggung jawab Pemerintah Pusat atau Pemerintah Daerah dan pengembang atau pembangun dalam penanganan dampak Lalu Lintas sebagaimana dimaksud dalam huruf h; j.rencana pemantauan dan evaluasi; dan k. gambaran umum lokasi yang akan dibangun atau dikembangkan. (2) Rekomendasi teknis penanganan dampak Lalu Lintas sebagaimana dimaksud dalam Pasal 5 ayat (2) huruf b paling sedikit memuat: a. analisis kondisi Lalu Lintas dan Angkutan Jalan saat ini; SK No 093133 Ab. simulasi PRES IDEN REPUBLIK INDONESIA -9- b. simulasi kinerja Lalu Lintas yang dilakukan terhadap analisis dampak Lalu Lintas; c. rekomendasi dan rencana implementasi penanganan dampak Lalu Lintas; d. rincian tanggung",
      "metadata": {
        "page_start": 1,
        "page_end": 2
      }
    },
    {
      "text": "dan rencana implementasi penanganan dampak Lalu Lintas; d. rincian tanggung jawab Pemerintah Pusat atau Pemerintah Daerah dan pengembang atau pembangun dalam penangarlan dampak Lalu Lintas sebagaimana dimaksud dalam huruf c; e. rencana pemantauan dan evaluasi; dan f. gambaran umum lokasi yang akan dibangun atau dikembangkan. (3) Pemenuhan standar teknis penanganan dampak La-lu Lintas sebagaimana dimaksud dalam Pasal 5 ayat (2) huruf c angka 1 meliputi: a. rekomendasi dan rencana implementasi penanganan dampak Lalu Linta.s; b. rincian tanggung jawab Pemerintah Pusat atau Pemerintah Daerah dan pengembang atau pembangun dalam penanganan dampak Lalu Lintas sebagaimana dimaksud dalam huruf a; dart c. rencana pemantauan dan evaluasi. Pasal 7 Hasil analisis dampak Lalu Lintas sebagaimana dimaksud dalam Pasal 5 ayat (2) harus mendapat persetujuan da a. Menteri, untuk Jalan nasional; b. gubernur, untuk Jalan provinsi; c. bupati, untuk Jalan kabupaten danlatau Jalan desa; atau d. walikota, untuk Jalan kota. SK No 093134 APasal 8 PRES IDEN REPUBLIK INDONESIA -10- Pasa] 8 (1) Untuk memperoleh persetujuan sebagaimana dimaksud dalam Pasal 7, pengembang atau pembangun harus menyampaikan hasil analisis dampak Lalu Lintas sesuai dengan ska-la dampak bangkitan Lalu Lintas kegiatan yang ditimbulkan kepada Menteri, gubernur, atau bupati/walikota sesuai dengan kewenangannya. (2) Penyampaian hasil analisis dampak Lalu Lintas sebagaimana dimaksud pada ayat (1) dilakukan melalui sistem elektronik yang terintegrasi dengan P erizinan Berusaha lingkungan hidup. (3) Sistem elektronik sebagaimana dimaksud pada ayat (2) dilaksanakan pada Kementerian, kementerian yang menyelenggarakan urusan pemerintahan di bidang lingkungan hidup dan kehutanan, dan lembaga pemerintah yang menyelenggarakan urusan pemerintahan di bidang koordinasi penanaman modal melalui pelayanan terpadu satu pintu. (4) Menteri, gubernur, atau bupati/walikota sebagaimana dimaksud pada ayat (1) memberikan persetuiuan paling lama 3 (tiga) hari kerja setelah seluruh dokumen lengkap. (5) Ketentuan lebih lanjut mengenai tata cara pemberian persetujuan hasil analisis dampak Lalu Lintas diatur dengan Peraturan Menteri. Pasal 9 (1Dalam hal hasil analisis dampak Lalu Lintas berupa dokumen analisis dampak Lalu Lintas untuk kegiatan dengan skala dampak bangkitan Lalu Lintas yang tinggi, maka persetujuan sebagaimana dimaksud dalam Pasal8 diberikan setelah mendapat persetujuan teknis dari tim evaluasi penilai analisis dampak Lalu Lintas. SK No 093135 A(2) Tim... PRES IDEN REPUBLIK INDONESIA - 11- (2) Tim evaluasi penilai analisis dampak Lalu Lintas sebagaimana dimaksud pada ayat (1) dibentuk oleh Menteri, gubernur, atau bupati/walikota sesuai dengan kewenangannya. (3) Tim evaluasi penilai analisis dampak Lalu Lintas sebagaimana dimaksud pada ayat (1) merupakan unsur pembina sarana dan Prasa-rana Lalu Lintas dan Angkutan Jalan, yang berjumlah sebanyak 3 (tiga) orang. Pasal 10 Tim evaluasi penilai analisis dampak Lalu Lintas sebagaimana dimaksud dalam Pasal 9 mempunyai tugas: a. melakukan penilaian terhadap hasil analisis darnpak Lalu Lintas yang berupa dokumen analisis dampak La-lu Lintas untuk kegiatan dengan skala dampak bangkitan Lalu Lintas yang tinggi; dan b. menilai kelayakan persetujuan yang diusulkan dalam hasil analisis dampak Lalu Lintas. Pasal 1 1 (1) Dalam hal hasil analisis dampak Lalu Lintas telah memenuhi persyaratan sebagaimana dimaksud dalam Pasal 6, Menteri, gubernur, atau bupati/walikota sesuai dengan kewenangannya meminta kepada pengembang atau pembangun untuk membuat surat pernyataan kesanggupan melaksanakan semua kewajiban analisis dampak",
      "metadata": {
        "page_start": 2,
        "page_end": 2
      }
    },
    {
      "text": "untuk membuat surat pernyataan kesanggupan melaksanakan semua kewajiban analisis dampak Lalu Lintas. (2) Surat pernyataan kesanggupan sebagaimana dimaksud pada ayat (1) ditandatangani oleh penanggung jawab perusahaan di atas materai. (3) Surat pernyataan kesanggupan sebagaimana dimaksud pada ayat (2) merupakan bagian yang tidak terpisahkan dari hasil analisis dampak LaIu Lintas. ' (4) Kewajiban sebagaimana dimaksud pada ayat (1) harus terpenuhi sebelum dan selama pusat kegiatan, permukiman, dan infrastruktur dioperasikan. SK No 093136 APasal12... PRES IDEN REPUBLIK INDONESIA -72- Pasal 12 (1) Terhadap pelaksanaan pemenuhan kewajiban pengembang atau pembangun yang tercantum dalam persetujuan hasil analisis dampak Lalu Lintas sebagaimana dimaksud daiam Pasal 11 dilakukan monitoring dan evaluasi secara berkala. (2) Monitoring dan evaluasi secara berkala sebagaimana dimaksud pada ayat (1) dilaksanakan oleh tim monitoring dan evaluasi yang dibentuk oleh Menteri, gubernur, atau bupati/walikota sesuai dengan kewenangannya. (3) Tim monitoring dan evaluasi sebagaimana dimaksud pada ayat (2) diketuai oleh instansi pembina di bidang sarana dan Prasarana Lalu Lintas dan Angkutan Jalan serta beranggotakan unsur dari instansi pembina di bidang Jalan dan Kepolisian Negara Republik Indonesia. Pasal L3 Tim monitoring dan evaluasi sebagaimana dimaksud dalam Pasal 12 ayat (3) mempunyai tugas: a. melakukan pemantauan dan pengawasan terhadap pelaksanaan persetuju€rn hasil analisis dampak Lalu Lintas baik pada masa kontruksi maupun operasional kegiatan usaha; dan b. melakukan evaluasi terhadap pelaksanaan dan pemenuhan atas persetujuan hasil analisis dampak Lalu Lintas yang telah ditetapkan. Pasal 14 (1) Setiap pengembang atau pembangun yang melanggar pernyataan kesanggupan sebagaimana dimaksud dalam Pasal 11 ayat (1) dikenai sanksi administratif oleh pemberi izin sesuai dengan ketentuan peraturan perundang-undangan. Sl( No 093137 A(2) Sanksi PRES IDEN REPUBLIK INDONESIA -13 (2) Sanksi administratif sebagaimana dirnaksud pada ayat (1) henrpa: a. peringatan tertulis; b. penghentian sementara kegiatan/pelayanan umum; c. denda administratif; dan/atau d. pembatalan persetujuan hasil analisis dampak Lalu Lintas dan/ atau Perizinan Berusaha. Pasal 15 (1) Sanksi administratif berupa peringatan tertulis sebagaimana dimaksud dalam Pasal 14 ayat (2) huruf a dikenai sebanyak 3 (tiga) kali dengan jangka waktu masing-rnasing 30 (tiga puluh) hari kaiender. (2) Dalam hal pengembang atau pembangun tidak melaksanakan kewajiban setelah berakhirnya jangka waktu peringatan tertulis ketiga, . dikenai sanksi administratif berupa penghentian sementara kegiatan/pelayanan umum selama 30 (tiga puluh) hari kalender. (3) Dalam hal pengembang atau pembangun tetap tidak melaksanakan kewajiban setelah berakhirnya jangka waktu sebagaimana dimaksud pada ayat (2), dikenai denda administratif paling banyak 1% (satu persen) dari nilai kewajiban yang harus dipenuhi oleh pengembang atau pemhangun sebagaimana dimaksud dalam Pasal 11 ayat (4). (41 Dalam waktu 10 (sepuluh) hari kalender sejak tanggal pengenaan sanksi denda administratif atau 9O (sembilan puluh) hari kalender sejak pembayaran denda, pengembang atau pembangun tidak melaksanakan kewajibannya, maka persetujuan hasil analisis dampak Lalu Lintas dan/atau Perizinan Berusaha sebagaimana dimaksud dalam Pasal 4 dibatalkan SK No 093138 ABAB III PRES IDEN REPUBLIK INDONESIA -74- BAB III KENDARAAN Pasal 16 (1) Pengujian Kendaraan Bermotor hanya dapat dilakukan oleh unit pelaksana pengujian Kendaraan Bermotor yang memiliki: a. fasilitas dan peralatan pengujian yang akurat, sistem dan prosedur pengujian, dan sistem informasi manajemen penyelenggaraan pengujian; dan b. tenaga penguji yang",
      "metadata": {
        "page_start": 2,
        "page_end": 2
      }
    },
    {
      "text": "sistem informasi manajemen penyelenggaraan pengujian; dan b. tenaga penguji yang memiliki Sertifikat Kompetensi penguji Kendaraan Bermotor. (2) Peralatan pengujian sebagaimana dimaksud pada ayat (1) wajib dipelihara dan dikalibrasi secara berkala. Pasal 17 (1) Uji tipe sebagaimana dimaksud dalam Pasal 121 ayat (3) huruf a Peraturan Pemerintah Nomor 55 Tahun 2Ol2 tentang Kendaraan dilaksanakan oleh Pemerintah Pusat melalui unit pelaksana pengujian tipe KendaraarL Bermotor dan dapat dikerjasamakan dengan badan usaha milik nega-ra, badan usaha milik daerah, badan usaha milik desa. dan swasta. (2) Uji tipe sebagaimana dimaksud pada ayat (1) terdiri atas: a. pengujian fisik terhadap pemeriksaan persyaratan teknis dan pengujian laik Jalan terhadap landasan Kendaraan Bermotor dan Kendaraan Bermotor dalam keadaan lengkap; dan b. penelitian rancang bangun dan rekayasa Kendaraan Bermotor. (3) uji... SK No 093120 A PRES IDEN REPUBLIK INDONESIA -15- (3) Uji tipe Kendaraan Bermotor yang dapat dikerjasamakan dengan badan usaha milik negara, badan usaha milik daerah, badan usaha milik desa, dan swasta sebagaimana dimaksud pada ayat (1) berupa kegiatan: a. pembangunan, pemeliharaan, perawatan, dan perbaikan fasilitas pengujian tipe Kendaraan Bermotor; dan/atau b. pengadaan, pemeliharaa.n, perawatan, perbaikan, penggantian, dan kalibrasi peralatan uji tipe Kendaraan Bermotor. (4) Uji tipe sebagaimana dimaksud pada ayat (1) dikenai biaya sesuai dengan ketentuan peraturan perundang- undangan. (5) Biaya sebagaimana dimaksud pada ayat (41ditetapkan sebagai penerimaan negara bukan pajak dan disetorkan ke kas negara. (6) Kendaraan Bermotor yang dinyatakan lulus uji tipe sebagaimana dimaksud pada ayat (1) dapat dibuat, dirakit, atau diimpor secara massal. (71 Setiap unit Kendaraan Bermotor sebagaimana dimaksud pada ayat (6) wajib dilakukan registrasi uji tipe. Pasal 18 Ketentuan lebih lanjut mengenai pemeriksaan persyaratan teknis dan pengujian laik Jalan terhadap landasan Kendaraan Bermotor dan Kendaraan Bermotor dalam keadaan lengkap diatur dengan Peraturan Menteri. Pasal 19 (1) Pengujian fisik terhadap pemeriksaan persyaratan teknis dan pengujian laik Jalan Kendaraan Bermotor yang memenuhi persyaratan dinyatakan lulus dan yang tidak memenuhi persyaratan dinyatakan tidak lulus. SK No 093181 A(2) Kendaraan. . . PRES IDEN REPUBLIK INDONESIA -16- (2) Kendaraan Bermotor yang dinyatakan tidak lulus uji fisik sebagaimana dimaksud pada ayat (1) harus disampaikan secara tertulis disertai dengan: a. alasan tidak lulus uji fisik; b. itemyang tidak lulus uji fisik; c. perbaikan yang harus dilakukan; dan d. batas waktu mengajukan pengujian ulang. (3) Kendaraan Bermotor yang dinyatakan lulus uji fisik sebagaimana dimaksud pada ayat (1) diberikan bukti lulus uji tipe oleh Menteri, berupa: a. sertifikat uji tipe dilengkapi dengan pengesahan hasil uji fisik untuk Kendaraan Bermotor yang diuji fisik dalam keadaan lengkap; atau b. sertifikat uji tipe landasan dilengkapi dengan pengesahan hasil uji fisik untuk landasan Kendaraan Bermotor yang diuji fisik dalam bentuk landasan. (4)Ketentuan lebih lanjut mengenai bentuk dan tata cara penerbitan sertifikat uji tipe diatur dengan Peraturan Menteri. Pasal 20 (1) Penelitian rancang bangun dan rekayasa Kendaraall' Bermotor sebagaimana dimaksud dalam Pasal 17 a5rat {21huruf b dilakukan terhadap desain: a. rumah-rumah; b. bak muatan; c. tangki; d. kereta gandengan; e\" kereta tempelan; dan SK Nlc 0q3132 Af. Kendaraan PRES tDEN REPUBLIK lNDONESIA -17- f. Kendaraan Bermotor yang dimodifikasi yang menyebabkan perubahan tipe berupa dimensi",
      "metadata": {
        "page_start": 2,
        "page_end": 3
      }
    },
    {
      "text": "Kendaraan Bermotor yang dimodifikasi yang menyebabkan perubahan tipe berupa dimensi dan kemampuan daya angkut. (2) Terhadap penelitian rancang bangun dan rekayasa Kendaraan Bermotor sebagaimana dimaksud pada ayat (1) dikenai biaya sesuai dengan ketentuan peraturan perundan g-undangan. (3) Biaya sebagaimana dimaksud pada ayat (2) ditetapkan sebagai penerimaan negara bukan pajak dan disetorkan ke kas negara. Pasal 21 (1) Pelaksanaan penelitian rancang bangun dan rekayasa Kendaraan Bermotor sebagaimana dimaksud dalam Pasal 132 Peraturan Pemerintah Nomor 55 Tahun 2Ot2 tentang Kendaraan dituangkan dalam berita acara hasil penelitian oleh pimpinan unit pelaksana uji tipe. (2) Dalam hal berita acara hasil penelitian sebagaimana dimaksud pada ayat (1) menyatakan bahwa rancang bangun dan rekayasa Kendaraan Bermotor tidak memenuhi persyaratan teknis dan laik Jalan, berita acara disampaikan kepada pemohon atau pemilik Kendaraan Bermotor dengan tembusan kepada Menteri. (3) Dalam hal berita aca-ra hasil penelitian sebagaimana dimaksud pada ayat (1) menyatakan bahwa rancang bangun dan rekayasa Kendaraan Bermotor memenuhi persyaratan teknis dan laik Jalan, berita acara disampaikan kepada Menteri. (4) Berdasarkan berita acara hasil penelitian sebagaimana dimaksud pada ayat (3), Menteri menerbitkan Keputusan Pengesahan Rancang Bangun dan Rekayasa Kendaraan Bermotor. (5) Ketentuan lebih lanjut mengenai penelitian rancang barigun dan rekayasa Kendaraan Bermotor diatur dengan Peraturan Menteri. SK No 093140 APasal22 PRES IDEN REPUBLIK ]NDONESIA -18- Pasal.22 (1) Kendaraan Bermotor, kereta gandengan, kereta tempelan, dan Kendaraan Bermotor yang dimodifikasi yang telah dilakukan registrasi uji tipe diberikan sertifikat registrasi uji tipe oleh Menteri. (2) Penerbitan sertifikat registrasi uji tipe sebagaimana dimaksud pada ayat (l) dikenai biaya sesuai dengan ketentuan peraturan perundang-undangan. (3) Biaya sebagaimana dimaksud pada ayat (2) ditetapkan sebagai penerimaan negara bukan pajak dan disetorkan ke kas negara. (4) Ketentuan lebih lanjut mengenai sertifikat registrasi uji tipe diatur dengan Peraturan Menteri. Pasal 23 (1) Unit pelaksana uji tipe sebagaimana dimaksud dalam Pasal 17 ayat (1) dibentuk oleh Menteri. (2) Unit pelaksana uji tipe sebagaimana dimaksud pada ayat (1) harus menyediakan fasilitas dan peralatan pengujian serta tenaga penguji yang memiliki kompetensi. (3) Untuk penyediaan fasilitas, peralatan pengujian, dan/atau tenaga penguji yang memiliki kompetensi, unit pelaksana uji tipe dapat bekerjasama dengan badan usaha milik negara, badan usaha milik daerah, badan usaha milik desa, dan swasta. (4) Fasilitas dan peralatan pengujian sebagaimana dimaksud pada ayat (2) harus dirawat dan/atau diperbaiki apabila rusak, serta dikalibrasi secara berkala. (5) Perawatan dan/atau perbaikan sertalibrasi sebagaimana dimaksud pada ayat (4) dapat dikerjasamakan dengan badan usaha milik negara, badan usaha milik daerah, badan usaha milik desa, dan swasta. SK No 093141 A(6) Unit . PRE'S IDEN REPUBLIK INDONESIA -t9- (6) Unit pelaksana ujisistem informasi Kendaraan Bermotortipe danharus menyelenggarakan komunikasi pengujian Pasa124 (1) Uji berkala sebagaimana dimaksud dalam Pasal 121 ayat (3) huruf b Peraturan Pemerintah Nomor 55 Tahun 2Ol2 tentang Kendaraan wajib bagi mobil Penumpang umum, mobil bus, mobil barang, kereta gandengan dan kereta tempelan yang dioperasikan di Jalan. (21 Pengujian berkala sebagaimana dimaksud pada ayat (1) meliputi kegiatan: a. pendaftaran Kendaraan Bermotor wajib uji berkala; b. uji berkala pertama; dan c. uji berkala perpanjangan masa berlaku. (3) Uji berkala sebagaimana dimaksud pada ayat (1) dilaksanakan oleh:",
      "metadata": {
        "page_start": 3,
        "page_end": 3
      }
    },
    {
      "text": "(3) Uji berkala sebagaimana dimaksud pada ayat (1) dilaksanakan oleh: d.'. unit pelaksana pengujian Pemerintah Daerah kabupaten/kota sesuai dengan norrna, standar, prosedur, dan kriteria yang ditetapkan oleh Menteri; b. unit pelaksana agen tunggal pemegang merek yang mendapat Perizinan Berusaha dari Menteri; atau c. unit pelaksana pengujian swasta yang mendapatkan Perizinan Berusaha dari Menteri. (4) Uji berka-la pertama dan uji berkala perpanjangan masa berlaku sebagaimana dimaksud padaayat (2) huruf b dan huruf c meliputi: a. pemeriksaanpersyaratanteknis; b. pengujian persyaratan laik Jalan; dan c. pemberian bukti lulus uji. SK No 093142 A(5) Unit PRES IDEN REPUBLIK INDONESIA -20- (5) Unit pelaksana agen tunggal pemegang merek dan unit pelaksana pengujian swasta sebagaimana dimaksud pada ayat (3) huruf b dan huruf c hanya rnelaksanakan uji berkala perpanjangarl masa berlaku. (6) Unit pelaksana uji berkala sebagaimana dimaksud pada ayat (3) wajib: a. melaksanakan pengujian sesuai dengan akreditasi unit pelaksana pengujian dan sertifikasi tenaga penguji; b. mempertahankan mutu pengujian yang diselenggarakan; c. membuat rencana dan pelaporan secara berkala setiap penyelenggara pengujian kepada Menteri ; d. menggunakan peralatan pengujian; dan e. mengikuti tata cara pengujian. (7) Dalam hal unit pelaksana pengujian Pemerintah Daerah kabupatenlkota tidak memenuhi norma, standar, prosedur, dan kriteria sebagaimana dimaksud pada ayat (3) huruf a, pelaksanaan uji berkala dilakukan oleh unit pelaksana pengujian yang ditetapkan oleh Menteri. Pasal 25 (1) Unit pelaksana pengujian berkala Kendaraan Bermotor sebagaimana dimaksud dalam Pasal 24 ayat (3) dapat menyelenggarakan pengujian berkala Kendaraan Bermotor setelah mendapat akreditasi dari Menteri, (2) Untuk memperoleh akreditasi sebagaimana dimaksud pada ayat (1), unit pelaksana trji berkala Kendaraan Bermotor harus memenuhi persyaratan: a. lokasi; b. kompetensi tenaga penguji Kendaraan Bermotor; standar fasilitas prasarana dan peralatan pengujian berkala Kendaraan Bermotor; SK No 093143 Ad.standar... PRES IDEN REPUBLIK INDONESIA -2r- d. standar peralatan pengujian Kendaran Bermotor; e. keakurasian peralatan pengujian Kendaran Bermotor; f\" sistem dan tata cara pengujian Kendaraan Bermotor; dan g. sistem informasi uji berkala Kendaraan Bermotor. (3) Akreditasi sebagaimana dimaksud pada ayat (1) berlaku paling lama 5 (lima) tahun dan dapat diperpanjang setelah memenuhi persyaratan sesuai dengan ketentuan. (4\\ Ketentuan lebih lanjut mengenai akreditasi unit pelaksana pengujian berkala Kendaraan Bermotor diatur dengan Peraturan Menteri. Pasal 26 (1) Pengembangan rancang bangun Kendaraan Bermotor dan pengembangan riset dan rancang bangun Kendaraan Bermotor dilakukan oleh: a\" Pemerintah Pusat; b. Pemerintah Daerah; c. badan hukum; d. lembaga penelitian; dan/atau e. perguruan tinggi. (2) Pengembangan rancang bangun Kendaraan Bermotor sebagaimana dimaksud pada ayat (1) wajib memperhatikan: a. dimensi utama dan konstruksi Kendaraan Bermotor; b. kesesuaian material; c. kesesuaian motor penggerak; Sl( No 093144 Ad. kesesuaian PRES IDEN REPUBLIK INDONESIA -22- d. kesesuaian daya dukung Jalan; e. bentuk fisik Kendaraan Bermotor; f. dimensi, konstruksi, posisi, dan jarak tempat duduk; g. posisi lampu; h. jumlah tempat duduk; i. dimensi dan konstruksi bak muatan/volume tangki; j. peruntukan Kendaraan Bermotor; dan k. fasilitas keluar darurat. (3) Rancang bangun sebagaimana dimaksud pada ayat (2) harus mendapatkan pengesahan dari Menteri. Pasal 27 (1) Pengesahan pengembangan rancang bangun Kendaraan Bermotor dan pengembangan riset dan rancang bangun Kendaraan Bermotor sebagaimana dimaksud dalam Pasal 26 dilakukan melalui uji",
      "metadata": {
        "page_start": 3,
        "page_end": 3
      }
    },
    {
      "text": "Kendaraan Bermotor sebagaimana dimaksud dalam Pasal 26 dilakukan melalui uji tipe Kendaraan Bermotor (21 Ketentuan lebih lanjut mengenai pengesahan rancang bangun Kendaraan Bermotor diatur dengan Peraturan Menteri. Pasal 28 (1) Bengkel umum Kendaraan Bermotor berfungsi untuk memperbaiki dan merawat Kendaraan Bermotor agar tetap memenuhi persyaratan teknis dan laik Jalan. (2) Bengkel umum sebagaimana dimaksud pada ayat (1) wajib memenuhi persyaratan teknis bengkel umum Kendaraan Bermotor (3) Penyelenggaraan bengkel umum sebagaimana dimaksud pada ayat (1) harus memenuhi Perizinan Berusaha dan memiliki sertifikasi bengkel umum derri menteri yan g menyelen ggarakan urusan pemeri ntah an di bidang perindustrian. SK No 093145 A(4) Persyaratan... PRES IDEN REPUBLIK INDONESIA -23- (41 Persyaratan teknis bengkel umum Kendaraan Bermotor sebagaimana dimaksud pada ayat (2) sesuai dengan tingkat pemenuhan terhadap persyaratan sistem mutu, mekanik, fasilitas dan peralatan, serta manajemen informasi. (5) Ketentuan lebih lanjut mengenai persyaratan teknis, klasifikasi, dan sertilikasi bengkel umum diatur dengan peraturan menteri yang menyelenggarakan urusan pemerintahan di bidang perindustrian. Pasal 29 (1) Pengawasan terhadap bengkel umum Kendaraan Bermotor sebagaimana dimaksud dalam Pasal 28dilaksanakan oleh Pemerintah Daerah kabupaten/kota sesuai dengan norma, standar, prosedur, dan kriteria yang ditetapkan oleh menteri yang menyelqnggarakan urusan pemerintahan di bidang perindustrian. (2) Pengawasan terhadap bengkel umum Kendaraan Bermotor sebagaimana dimaksud pada ayat (1) dilakukan audit dan inspeksi terhadap kinerja pelayanan yang diberikan (3) Pengawasan terhadap bengkel umum Kendaraan Bermotor sebagaimana dimaksud pada ayat (1) dilaksanakan secara online dan realtime. Pasal 30 (1) Bengkel umum Kendaraan Bermotor sebagaimana dimaksud dalam Pasal 173 Peraturan Pernerintah Nomor 55 Tahun 2Ol2 tentang Kendaraan dapat menjadi unit pelaksana uji berkala Kendaraan Bermotor (21 Bengkel umum yang m kukan uji berkala sebagaimana dimaksud pada ayat (1) wajib memenuhi persyaratan: SK No 093146 Aa.meniiliki... PRES IDEN REPUBLIK INDONESIA -24- a. memiliki peralatan dan fasilitas uji berkala; b. memiliki Perizinan Berusaha bengkel Kendaraan Bermotor dari menteri yang menyelenggarakan urusan pemerintahan di bidang perindustrian; dan c. memenuhi hasil analisis dampak Lalu Lintas yarlg merupakan bagian dari dokumen analisis mengenai dampak lingkungan atau upaya pengelolaan lingkungan hidup dan upaya pemantauan lingkungan hidup. (3) Penetapan bengkel umum Kendaraan Bermotor menjadi unit pelaksana uji berkala Kendaraan Bermotor dilakukan oleh Menteri. (41 Ketentuan lebih lanjut mengenai pemberian akreditasi dan penetapan bengkel umum menjadi unit pelaksana uji berkala diatur dengan Peraturan Menteri. Pasal 31 (1) Setiap pemegang Perizinan Berusaha pengujian berkala Kendaraan Bermotor sebagaimana dimaksud dalam Pasal 24 ayat (3) huruf b dan huruf c yang melanggar ketentuan Perizinan Berusaha dikenai sanksi administratif, sebagai berikut: a. peringatan tertulis; b. dendaadministratif; c. pembekuanPerizinan Berusaha; dan f atau d. pencabutanPerizinan Berusaha. (2) Sanksi administratif berupa peringatan tertulis sebagaimana dimaksud pada ayat (1) huruf a dikenai paling banyak 2 (dua) kali dengan jangka waktu masing-masing 30 (tiga puluh) hari kalender. (3) Dalam hal pemegang Perizinan Berusaha tetap tidak melaksanakan kewajiban setelah berakhirnya jangka waktu peringatan tertulis kedua sebagaimana dimaksud pada ayat (2), dikenai denda administratif sebesar Rp24.000.000,00 (dua puluh empat juta rupiah). SK No 093221 A(a) Apabila... PRES IDEN REPUBLIK lNDONESIA -25- (4) Apabila dalam jangka waktu 30 (tiga puluh) hari kalender sejak pengenaan denda administratif",
      "metadata": {
        "page_start": 3,
        "page_end": 4
      }
    },
    {
      "text": "waktu 30 (tiga puluh) hari kalender sejak pengenaan denda administratif pemegang Perizinan Berusaha tidak melakukan pembayaran denda dan melaksanakan perbaikan terhadap pelanggaran yang dilakukan, pemegang Perizinan Berusaha dikenai sanksi pembekuan Perizinan Berusaha. (5) Apabila dalam jangka waktu 30 (tiga puluh) hari kalender sej ak tanggal pembeku an P erizinan Berusaha sebagaimana dimaksud pada ayat (4) pemegang Perizinan Berusaha tidak melaksanakan perbaikan terhadap pelanggaran yang dilakukan, pemegang Perizinan Berusaha dikenai sanksi pencabutan Perizinan Berusaha. BAB IV JARINGAN LALU LINTAS DAN ANGKUTAN JALAN Pasa-l 32 (1) Kendaraan Bermotor yang dapat berlalu lintas di setiap kelas Jalan ditentukan berdasarkan ukuran, dimensi, muatan sumbu terberat, dan permintaan angkutan. (2) Kendaraan Bermotor yang dapat berlalu iintas i \"latankelas I ditentukan: a. ukuran lebar tidak melebihi 2.550 (dua ribu lima ratus lima puluh) milimeter; b. ukuran panjang tidak melebihi 18.000 (delapan belas ribu) milimeter; c. ukuran tinggi tidak melebihi 4.2OO (empat ribu dua ratus) milimeter; dan d. ukuran muatan sumbu terberat 10 (sepuluh) ton. (3) Kendaraan Bermotor yang dapat berlalu lintas di Jalan kelas II ditentukan: a. ukuran lebar tidak melebihi 2.550 (dua ribu lima ratus lima puluh) milimeter; b.ukuran... SK No 09i222 A PRES IDEN REPUBLIK INDONESIA -26- b. ukuran panjang tidak melebihi 12.000 (dua belas ribu) milimeter; c. ukuran tinggi tidak melebihi 4.2OO (empat ribu dua ratus) milimeter; dan d. ukuran muatan sumbu terberat 8 (delapan) ton. (41 Kendaraan Bermotor yang dapat berlalu lintas di Jalan kelas III ditentukan: a. ukuran lebar tidak melebihi 2.2OO (dua ribu dua ratus) milimeter; b. ukuran panjang tidak melebihi 9.000 (sembilan ribu) milimeter; c. ukuran tinggi tidak melebihi 3.500 (tiga ribu lima ratus) milimeter; dan d. ukuran muatan sumbu terberat 8 (delapan) ton. Pasal 33 (1) Jalan kelas III didesain dengan muatan sumbu terberat kurang dari 8 (delapan) ton hanya dapat dilewati Kendaraan Bermotor dengan ukuran: a. lebar tidak melebihi 2.2OO (dua ribu dua ratus) milimeter; b. panjang tidak melebihi 9.000 (sembilan ribu) milimeter; dan c. paling tinggi 3.500 (tiga ribu lima ratus) millimeter. (2) Penetapan muatan sumbu terberat sebagaimana dimaksud pada ayat (1) dilakukan oleh penyelenggara Jalan sesuai dengan kewenangan. Pasal 34 (1) Fasilitas penunjang sebagaimana dimaksud dalam Pasal 69 ayat (2) huruf b Peraturan Pemerintah Nomor 79 Tahun 2OI3 tentang Jaringan Lalu Lintas dan Angkutan Jalan merupakan fasilitas yang disediakandi Terminal sebagai penunjang kegiatan pokok Terminal. SK No 093223 A(2) Fasilitas PRES IDEN REPUBLIK INDONESIA -27 - (2) Fasilitas penunjang sebagaimana dimaksud pada ayat (1) dapat berupa: a. fasilitas penyandang cacat dan ibu hamil atau menyusui; b. pos kesehatan; c. fasilitas kesehatan; d. fasilitasperibadatan; e. pos polisi; f. alat pemadam kebakaran; dan g. fasilitas umum. (3) Fasilitas umum sebagaimana dimaksud pada ayat (2) huruf g meliputi: a. toilet; b. rumah makan; c. fasilitas telekomunikasi; d. tempat istirahat awak Kendaraan; e. fasilitas pereduksi pencemaran udara dan kebisingan; f. fasilitas pemantau kualitas udara dan gas buang; g. fasilitas kebersihan; h. fasilitas perbaikan ringan Kendaraan umum; i. fasilitasperdagangan, pertokoan; dan/atau j. fasilitas penginapan. (4) Jumlah dan jenis fasilitas penunjang sebagaimana dimaksud pada ayat (2) disesuaikan dengan tipe dan klasifikasi",
      "metadata": {
        "page_start": 4,
        "page_end": 4
      }
    },
    {
      "text": "sebagaimana dimaksud pada ayat (2) disesuaikan dengan tipe dan klasifikasi Terminal. Pasal 35 (1) Fasilitas Terminal harus menyediakan tempat untuk kegiatan usaha mikro dan kecil paling sedikit 30% (tiga puluh persen). SK No 093224 A(2) Penyediaan PRES IDEN REPUBLIK INDONESIA -28- (2) Penyediaan tempat usaha untuk kegiatan usaha mikro dan kecil dilaksanakan berdasarkan kebutuhan dengan memperhatikan persyaratan keselamatan dan keamanan. (3) Ketentuan lebih lanjut mengenai penentuan tempat usaha untuk kegiatan usaha mikro dan kecil diatur dengan Peraturan Menteri. Pasa-l 36 (1) Lingkungan kerja Terminal merupakan daerah yang diperuntukkan bagr fasilitas Terminal sebagaimana dimaksud dalam Pasal 69 Peraturan Pemerintah Nomor 79 Tahun 2Ol3 tentang Jaringan Lalu Lintas dan Angkutan Jalan. (2) Pengaturan dan pemanfaatan daerah lingkungan keda Terminal sebagaimana dimaksud pada ayat (1) menjadi tanggung jawab penyelenggara Terminal. (3) Lingkungan kerja Terminal sebagaimana dimaksud pada ayat (1) dikelola oleh penyelenggara Terminai clan digunakan untuk pelaksanaan pembangunarl, pengembangan, dan pengoperasian fasilitas Terminal. (4) Dalam hal Pemerintah Pusat sebagai penyelenggara Terminal sebagaimana dimaksud pada ayat (2), pelaksanaannya dapat dikerjasamakan dengan badan usaha milik negara, badan usaha milik daerah, badan usaha milik desa, koperasi, dan swasta. (5) Lingkungan kerja Terminal harus dimanfaatkan semaksimal mungkin untuk kegiatan penyelenggaraan Terminal Pasal 37 (1) Untuk kemudahan pengaturan naik turun Penumpang, perpindahan moda angkutan, keterpaduan, dan pengawasan angkutan orang, pada lokasi tertentu dapat dibangun Terminal Penumpang. SK No 093225 A(2) Kebutuhan PRES IDEN REPUBLIK INDONESIA -29 - (2) Kebutuhan luas lahan untuk pembangunan Terminal Penumpang sebagaimana dimaksud pada ayat (1) harus disesuaikan dengan perkiraan permintaan angkutan orang. (3) Pembangunan Terminal Penumpang sebagaimana dimaksud pada ayat (1) harus dilengkapi dengan: a. rancang bangun; b. buku kerja rancang bangun; c. rencana induk Terminal; dan d. dokumen analisis mengenai dampak lingkungan atau upaya pengelolaan lingkungan hidup dan upaya pemantauan lingkungan hidup yang telah mencakup analisis dampak Lalu Lintas. Pasal 38 Dokumen analisis mengenai dampak lingkungan atau upaya pengelolaan lingkungan hidup dan upaya pemantauan lingkungan hidup yang telatr mencakup analisis dampak LaIu Lintas sebagaimana dimaksud dalam Pasal 37 ayat (3) huruf d disusun dan diterbitkan sesuai dengan ketentuan peraturan perundang-undangan. Pasal 39 (1) Pembangunan Terminal Penumpang merupakan tanggung jawab Pemerintah Pusat atau Pemerintah Daerah. (2) Pembangunan Terminal Penumpang sebagaimana dimaksud pada ayat (1) dapat dikerjasamakan dengan badan usaha milik negara, badan usaha milik daerah, badan usaha milik desa, koperasi, dan swasta sesuai dengan ketentuan peraturan perundang-undangan. SK No 093226 APasal 40 PRES IDEN REPUBLIK INDONESIA -30- Pasal 40 (1) Pengoperasian Terminal Penumpang dilaksanakan Pemerintah Pusat, Pemerintah Daerah provinsi, atau Pemerintah Daerah kabupaten I kota. (2) Pengoperasian Terminal sebagaimana dimaksud pada ayat (1) meliputi kegiatan: a. perencanaan; b. pelaksanaan; dan c. pengawasan operasional. (3) Perencanaan dan pelaksanaan sebagaimana dimaksudpada ayat (2) huruf a dan huruf b dapat dikerjasamakan dengan badan usaha milik negara, badan usaha milik daerah, badan usaha milik desa, dan swasta. Pasal 4 1 Sebelum Terminal dioperasikan wajib dilakukan uji coba dan sosialisasi paling lambat 1 (satu) bulan sebelum dinyatakan beroperasi. Pasal42 (1) Penyelenggara Terminal Penumpang wajib melakukan pemeliharaan. (2) Pemeliharaan sebagaimana dimaksud pada ayat (1) meliputi kegiatan: a. menjaga keutuhan",
      "metadata": {
        "page_start": 4,
        "page_end": 4
      }
    },
    {
      "text": "sebagaimana dimaksud pada ayat (1) meliputi kegiatan: a. menjaga keutuhan dan kebersihan Terminal; b. menjaga keutuhan dan kebersihan pelataran Terminal serta perawatan rambu, marka, dan papan informasi; c. merawat saluran air; d. merawat instalasi listrik dan lampu penerangan; SK No 093221 Ae. merawat PRES IDEN REPUBLIK INDONESIA -31 - e. merawat fasilitas telekomunikasi; dan f. merawat sistem hgdrant serta fasilitas dan alat pemadam kebakaran. (3) Pemeiiharaan sebagaimana dimaksud pada ayat (2) wajib bekerjasama dengan usaha mikro dan kecil. (4) Bentuk pemeliharaan yang wajib dikerjasamakan sebagaimana dimaksud pada ayat (2) berupa: a. rutin; b. memfungsikan kembali; c. penggantian; dan d\" bersifat melengkapi. (5) Ketentuan lebih lanjut mengenai pemeliharaan fasilitas Terminal diatur dengan Peraturan Menteri. BAB V ANGKUTAN Pasal 43 (1) Pelayanan angkutan orang tidak dalam trayek dengan menggunakan taksi sebagaimana dimaksud dalam Pasal 47 huruf a Peraturan Pemerintah Nomor 74 Tahun 2Ol4 tentang Angkutan Jalan merupakan pelayanan dari pintu ke pintu dengan wilayah operasi dalam kawasan perkotaan. (21 Pelayanan angkutan orang tidak dalam trayek dengan menggunakan taksi sebagaimana dimaksud pada ayat (1) diklasifikasikan menjadi: a. reguler; dan b. eksekutif. SK No 093228 A(3) Kendaraan . PRES IDEN REPUBLIK INDONESIA -32- (3) Kendaraan yang dipergunakan untuk peiayanan angkutan orang tidak dalam trayek dengan menggunakan taksi sebagaimana dimaksud pada ayat (1) meliputi: a. mobil Penumpang sedan yang memiliki 3 (tiga) ruang; dan b. mobil Penumpang bukan sedan yang memiliki 2 (dua) ruang. (4) Sistem pembayaran pada pelayanan angkutan orang tidak dalam trayek dengan menggunakan taksi dilakukan berdasarkan argometer yang dilengkapi dengan alat pencetak bukti pembayaran maupun bukti elektronik berdasarkan aplikasi dalam jaringan. Pasal 44 (1) Penyelenggaraan fasilitas penimbangan yang dipasang secara tetap terdiri atas: a. pembangunan dan pengadaan; b. pengoperasian dan penutupan; c. pemeliharaan; d. pemanfaatan; e. pembinaan dan pengawasan; dan f. penilaian kinerja. (2) Penyelenggaraan fasilitas penimbangan yang dipasang secara tetap sebagaimana dimaksud pada ayat (1) dilaksanakan oleh Menteri dengan membentuk satuan pelayanan unit pelaksana penimbangan Kendaraan Bermotor. (3) Penyelengaraan fasilitas penimbangan yang dipasang secara tetap sebagaimana dimaksud pada ayat (1) dapat dikerjasamakan dengan badan usaha milik negara, badan usaha milik daerah, dan swasta sesuai dengan ketentuan peraturan perundang-undangan. Sl( No 093229 A(4) Penyelengaraan... PRES IDEN REPUBLIK INDONESIA -33- (41 Penyelenga-raan fasilitas penimbangan yang dipasang secara tetap yang dapat dikerjasamakan sebagaimana dimaksud pada ayat (3) meliputi kegiatan pembangunan dan pengadaan, pengoperasian, pemeliharaan, serta pemanfaatan. (5) Ketentuan lebih lan1ut mengenai penyelenggaraan fasilitas penimbangan sebagaimana dimaksud pada ayat (1) diatur dengan Peraturan Menteri. Pasal 45 (1) Fasilitas penimbangan yang dipasang secara tetap sebagaimana dimaksud dalam Pasal 44 dilengkapi dengan: a. fasilitas utama; dan b. fasilitas penunjang. (21 Fasilitas utama sebagaimana dimaksud pada ayat (1) huruf a terdiri atas: a. Jalan akses keluar masuk Kendaraan; b. Jalan sirkulasi Lalu Lintas di dalam wilayah operasi; bangunan kantor petugas; d. tempat pemeriksaan dan penindakan pelanggaran; e. tempat Parkir Kendaraan; f. alat penimbangan; g. alat pemindai data Kendaraan; h. alat pemindai dimensi Kendaraan; i. sistem informasi; j. detektor Kendaraan; k. Rambu Lalu Lintas dan Marka Jalan; SK No 093 l-56 A1. papan PRES lDEN REPUBLIK INDONESIA -34- 1.",
      "metadata": {
        "page_start": 4,
        "page_end": 5
      }
    },
    {
      "text": "093 l-56 A1. papan PRES lDEN REPUBLIK INDONESIA -34- 1. papan informasi; m. Alat Pemberi Isyarat Lalu Lintas; n. instalasi listrik; o. catu daya cadangan (genset) dan bangunannya; p. alat penerangan; dan q. toilet. (3) Fasilitas penunjang sebagaimana dimaksud pada ayat (1) huruf b terdiri atas: a. mes petugas; b. pagar; c. ruang terbuka hijau; d. tempat ibadah; e. kantin; f. papan/tampilan narna; g. tempat istirahat Pengemudi; dan h. jenis usaha komersil lainnya. (41 Fasilitas penunjang sebagaimana dimaksud pada ayat (3) dapat dikerjasamakan pemanfaatannya dengan badan usaha milik nega-ra, badan usaha milik daerah,dan swasta sesuai dengan ketentuan peraturan perundang-undangan. Pasa] 46 Pemegan g P erizinan Berusaha penyelenggaraan angkutan barang umum wajib: a. melaksanakan ketentuan yang ditetapkan dalam Perizinan Berusaha; dan b. melaksanakan sistem manajemen keselamatan. Pasal 47 (1) Pemerintah Pusat dan/atau Pemerintah Daerah pada trayek atau lintas tertentu dapat memberikan subsidi angkutan. (2) Pemberian. . . SK No 093 l -57 A PRES IDEN REPUBLIK INDONESIA -35- (2) Pemberian subsidi sebagaimana dimaksud pada ayat (1) dialokasikan pada anggaran pendapatan dan belanja negara dan/atau anggaran pendapatan dan belanja daerah. Pasal 48 Pemberian subsidi oleh Pemerintah Pusat dan/atau Pemerintah Daerah sebagaimana dimaksud dalam Pasal47 diberikan kepada: a. angkutan Penumpang umum dengan tarif kelas ekonomi pada trayek tertentu; dan/atau b. angkutan barang pada lintas tertentu. Pasal 49 (1) Angkutan Penumpang umum dengan tarif kelas ekonomi pada trayek tertentu sebagaimana dimaksud dalam Pasal 48 huruf a, ditentukan berdasarkan: a. faktor finansial; dan b. faktorketerhubungan. (2) Faktor finansial sebagaimana dimaksud pada avat (1) huruf a meliputi: a. trayek yang menghubungkan wilayah perbatasan dan/atau wilayah lainnya karena pertimbangarl aspek sosial politik; b. trayek angkutan perkotaan dan angkutan perdesaan khusus untuk pelajar dan/atau mahasiswa; c. trayek perkotaan dengan angkutan massal yang tarif keekonomiannya tidak tedangkau oleh daya beli masyarakat; atau d. trayek yang penetapan tarifnya di bawah biaya operasional yang ditetapkan oleh Pemerintah Pusat dan/atau Pemerintah Daerah. SK No 0931-58 A(3) Faktor . PRES IDEN REPUBLIK INDONESIA -36- (3) Faktor keterhubungan sebagaimana dimaksud pada ayat (t) huruf b meliputi: a. trayek yang menghubungkan wilayah terisolir dan/atau belum berkembang dengan kawasan perkotaan yang belum dilayani angkutan umum; dan b. trayek yang melayani perpindahan Penumpang dari angkutan penyeberangan perintis, angkutan laut perintis, atau angkutan udara perintis. (4) Ketentuan iebih lanjut mengenai penetapan trayek tertentu diatur dengan Peraturan Menteri. Pasal 50 Pemberian subsidi bagi angkutan barang pada lirrtas tertentu sebagaimana dimaksud dalam Pasal 48 huruf b dengan kriteria: a. menghubungkan wilayah tertinggal, terpencil, terluar, perbatasan, danf atau wilayah lainnya yang karena pertimbangan aspek sosial ekonomi harus dilayani; b. kawasan yang belum berkembang dan tidak terdapat pelayanan angkutan barang; c. mendorong pertumbuhan ekonomi; d. sebagai stabilisator pada suatu daerah tertentu dengan tarif angkutan yang lebih rendah dari tarif yang berlaku; e. melayani perpindahan barang ari angkutan laut perintis; f. melayani daerah transmigrasi dengan kawasan perkotaan; g. pemulihan daerah pasca bencana alam; dan/atau h. memberikan pelayanan angkutan balang yang terjangkau oleh masyarakat yang daya belinya masih rendah. SK No 0931-59 APasal 51 PRES IDEN REPUBLIK INDONESIA -37- Pasal 51 (1) Besarnya subsidi",
      "metadata": {
        "page_start": 5,
        "page_end": 5
      }
    },
    {
      "text": "PRES IDEN REPUBLIK INDONESIA -37- Pasal 51 (1) Besarnya subsidi angkutan sebagaimana dimaksud dalam Pasal 47 ayat (2) diberikan pada suatu trayek tertentu berdasarkan: a. selisih antara biaya pengoperasian yang dikeluarkan d engan pendapatan operasional yang diperoleh Perusahaan Angkutan Umum; atau b. biaya pengoperasian angkuta.n orang atauangkutan barang yang dikeluarkan oleh Perusahaan Angkutan Umum, jika pendapatan diambil oleh pihak lain yang ditunjuk oleh pemberi subsidi. (2) Ketentuan lebih lanjut mengenai perhitungan besaran subsidi angkutan sebagaimana dimaksud pada ayat (1) diatur dengan Peraturan Menteri setelah berkoordinasi dengan menteri yang menyelenggarakan urusan pemerintahan di bidang keuangan. Pasal 52 Pemberian subsidi penyelenggaraarl angkutan Penumpang umum dengan tarif kelas ekonomi pada trayek tertentu atau angkutan barang pada lintas tertentu kepada Perusahaan Angkutan Umum dilaksanakan oleh: a. Pemerintah Pusat, untuk angkutan antarkota antarprovinsi. angkutan antarkota dalam provinsi, angkutan perkotaan, atau angkutan perdesaan yang berdampak nasional, dan angkutan barang; b. Pemerintah Daerah provinsi, untuk angkutan antarkota dalam provinsi, angkutan perkotaan, atau angkutan perdesaan yang berdampak regional, dan angkutan barang; c. Pemerintah Daerah kabupaten, untuk angkutan perkotaan atau angkutan perdesaan yang berada dalam wilayah kabupaten, dan angkutan barang; dan/atau SK No 093160 Ad. Pemerintah dPRES IDEN REPUBLIK INDONESIA -38- Pemerintah Daeralr kota, untuk angkutan perkotaan atau angkutan perdesaan yang berada dalam wilayah kota, dan angkutan barang. Pasal 53 Pemilihan Perusahaan Angkutan Umum yang melayani angkutan Penumpang umum dengan tarif kelas ekonomi pada trayek tertentu atau angkutan barang bersubsidi sebagaimana dimaksud dalam Pasal 52 dilakukan melalui proses: a. pelelangan yang diikuti oleh badan usaha berbadan hukum yang bergerak di bidang angkutan umum; atau b. penunjukan langsung kepada badan usaha milik negara atau badan usaha milik daerah yang bergerak di bidang angkutan umum dengan prinsip penugasan. Pasal 54 (1) Masyarakat berhak untuk berperan serta da-lam penyelenggaraan angkutan Jalan. (21 Peran serta masyarakat sebagaimana dimaksud pada aya! (1) meliputi: a. memberikan masukan kepada instansi pembina Lalu Lintas dan Angkutan Jalan dalam penyempurnaan peraturan perundang-undangan, pedoman dan standar teknis di bidang angkutan Jalan; b. memantau pelaksanaan standar pelayanan angkutan umum yang dilakukan oleh Perusahaan Angkutan Umum; c: melaporkan penyelenggara angkutan umum yang tidak memiliki Perizinan Berusaha, dan/atau melakukan penyimpangan Perizinan Berusaha kepada instansi pemberi izin danlatau instansi yang diberi wewenang peraturan perundang- undangan untuk menegakkan ketentuan Perizinan Berusaha angkutan umum; SK No 09316i Ad. memberikan PRES IDEN REPUBLIK INDONESIA -39- d. rnemberikan masukan kepada instansi pembina Lalu Lintas dan Angkutan Jalan dalam perbaikan peiayanan angkutan umum; dan/atau e. memelihara sarana dan prasarana angkutan Jalan, dan ikut menjaga keamanan, keselamatan, ketertiban, dan kelancaran angkutan Jalan. (3) Peran serta masyarakat sebagaimana dimaksud pada ayat (21 disampaikan kepada instansi Pemerintah Pusat atau Pemerintah Daerah sesuai dengan tugas pokok dan fungsi instansi. (4) Pemerintah Pusat dan/atau Pemerintah Daerah mempertimbangkan dan menindaklanjuti masukan dan pendapat yang disampaikan oleh masyarakat sebagaimana dimaksud pada ayat (3). (5) Ketentuan lebih lanjut mengenai perari serta masyarakat diatur dengan Peraturan Menteri. BAB VI KETENTUAN LAIN-LAIN Pasal 55 (1) Pemerintah Pusat melakuka atas pelaksanaan Peraturan Pemerintah ini dengan memperhatikan perkembangan dan peningkatan ekosistem investasi dan kegiatan berusaha dalam rangka percepatan cipta kerja.",
      "metadata": {
        "page_start": 5,
        "page_end": 6
      }
    },
    {
      "text": "ekosistem investasi dan kegiatan berusaha dalam rangka percepatan cipta kerja. (2) Evaluasi sebagaimana dimaksud pada ayat (1) clilakukan oleh Menteri yang dikoordinasikan olehmenteri yang menyelenggarakzrn koordinasi, sinkronisasi, dan pengendalian unrsan kementerian dalam penyelengga-raan pemenntahan di bidang perekonomian. SK No 093162 APasal56... PRES IDEN REPUBLIK INDONESIA -40- Pasal 56 Dalam hal Peraturan Pemerintah ini memberikan pilihan tidak mengatur, tidak lengkap, atau tidak jelas, dan/atau adanya stagnasi pemerintahan, Menteri dapat melakukan diskresi untuk mengatasi persoalan konkret dalam penyelenggaraan urusan pemerintahan di bidang Lalu Lintas dan Angkutan Jalan. BAB VII KETENTUAN PERALIHAN Pasa-l 57 Ketentuan pelaksanaan Perizinan Berusaha yang diatur dalam Peraturan Pemerintah ini tidak berlaku bagi pelaku usaha/pihak yang telah mendapatkan Perizinan Berusaha sebelum Peraturan Pemerintah ini berlaku, kecuali ketentuan tersebut lebih menguntungkan bagi pemegang P erizinan Berusaha dimaksud \" Pasa_t 58 Pada at Peraturan Pemerintah ini mulai berlaku, Perizinan Berusaha yang sudah terb-it masih tetap berlaku sampai dengan berakhirny a P erizinan Beru saha tersebut. BAB VIII KETENTUAN PENUTUP Pasa-l 59 Perizinan Berusaha di bidang Lalu Lintas dan Angkutan Jalan dilaksanakan sesuai dengan ketentuan peraturan p e run d an g- undan gan men genai p e nyelen ggaraan P er rzinast Berusaha berbasis risiko. SK No 093163 APasal 6O PRES IDEN REPUBLIK INDONESIA -4t- Pasal 60 Pada saat Peraturan Pemerintah ini mulai berlaku, semua peraturan pelaksanaan dari Peraturan Pemerintah yang telah diubah dengan Peraturan Pemerintah ini dinyatakan tetap berlaku sepanjang tidak bertentangan dengan Peraturan Pemerintah ini. Pasal 61 (1) Pada saat Peraturan Pemerintah ini mulai berlaku a.Pasal 47, Pasal 48, Pasal 49, Pasal 50, Pasal 51, Pasal 52, Pasal 53, Pasal 54, Pasal 55, Pasal 56, Pasal 57, Pasal 58, dan Pasal 59 Peraturan Pemerintah Nomor 32 Tahun 2}ll tentang Manajemen dan Rekayasa, Analisis Dampak, serta Manajemen Kebutuhan Lalu Lintas (Lembaran Negara Republik Indonesia Tahun 2017 Nomor 61, Tambahan Lembaran Negara Republik Indonesia Nomor 5221); Pasa-l 122, Pasd, 123, Pasal I24, Pasd 125, Pasal l27,Pasal 129, Pasal 130, Pasal 131, Pasal 133, Pasal 134, Pasal I4O, Pasal 143, Pasal 16O, Pasal 161, Pasal 172, dan Pasal 174 Peraturan Pemerintah Nomor 55 Tahun 2Ol2 tentang Kendaraan (Lembaran Negara Republik Indonesia Tahun 2072 Nomor 12O, Tambahan Lembaran Negara Republik Indonesia Nomor 5317); Pasa-l 19, Pasal 20, Pasal 70, Pasal 73, Pasal 74, Pasal 77, Pasal 78, Pasal 79, Pasal 81, Pasal 86, dan Pasal 101 Peraturan Pemerintah Nomor 79 Tahun 2Ol3 tentang Jaringan LaIu Lintas dan Angkutan Jaian (Lembaran Negara Republik Indonesia Tahun 2Ol3 Nomor 193, Tambahan Lembaran Negara Republik Indonesia Nomor 5468); danb c SK No 093164 Ad. Pasal PRES IDEN REPUBLIK INDONESIA -42- d. Pasal 42, Pasd.65, Pasal 67, Pasal 68, Pasal 72, Pasal 78 ayat (1), Pasal 107, Pasa-l 108, Pasal 109, Pasal 110, Pasal 111, dan Pasal 120 Peraturan Pemerintah Nomor 74 Tahun 2Ol4 tentang Angkutan Jalan (Lembaran Negara Republik Indonesia Tahun 2Ol4 Nomor 260, Tambahan Lembaran Negara Republik Indonesia Nomor 5se4), dicabut dan dinyatakan tidak berlaku. (2) Terhadap pasal yang dicabut sebagaimana dimaksud pada ayat (1), yang menjadi acuan pada: a. Peraturan Pemerintah Nomor 55 Tahun 2Ol2",
      "metadata": {
        "page_start": 6,
        "page_end": 6
      }
    },
    {
      "text": "menjadi acuan pada: a. Peraturan Pemerintah Nomor 55 Tahun 2Ol2 tentang Kendaraan (Lembaran Negara Republik Indonesia Tahun 2012 Nomor l2O, Tambahan Lembaran Negara Republik Indonesia Nomor 5317); b. Peraturan Pemerintah Nomor 79 Tahun 2Ol3 tentang Jaringan Lalu Lintas dan Angkutan Jalan (Lembaran Negdra Republik Indonesia Tahun 2073 Nomor 193, Tambahan Lembaran Negara Republik Indonesia Nomor 5468); dan c. Peraturan Pemerintah Nomor 74 Tah2OI4 tentang Angkutan Jalan (Lembaran Negara Republik Indonesia Tahun 2Ol4 Nomor 260, Tambahan Lembaran Negara Republik Indonesia Nomor 5594), pengacuannya menyesuaikan dengan pasal, ayat, hrrruf, atau angka sebagaimana diatur dalam Peraturan Pemerintah ini. Pasa] 62 Peraturan Pemerintah inimul diundangkan. SK No 093165 AAgar PRESIDEN REPUBLIK INDONESIA -43- Agar setiap orang mengetahuinya, memerintahkan pengundangan Peraturan Pemerintah ini dengan penempatannya dalam Lembaran Negara Republik Indonesia. Ditetapkan di Jakarta pada tanggal 2 Febnrari 2O2l PRESIDEN REPUBLIK INDONESTA, JOKO WIDODO Diundangkan di Jakarta pada tanggal 2 Februari2O2l MENTERI HUKUM DAN HAK ASASI MANUSIA REPUBLIK INDONESIA, YASONNA H. LAOLY LEMBARAN NEGARA REPUBLIK INDONESIA TAHUN 2O2I NOMOR 40 Salinan sesuai dengan aslinya KEMENTERTAN SEKRETARIAT NEGARA REPUBLIK INDONESIA BidangPerundang-undangan Hukrrm,ttd ttd * * \"tlKt SK No 085096 ASilvanna Djaman PRES IDEN REPUBLIK INDONES]A PENJELASAN ATAS PERATURAN PEMERINTAH REPUBLIK INDONESIA NOMOR 30 TAHUN 2O2I TENTANG PENYELENGGARAAN BIDANG LALU LINTAS DAN ANGKUTAN JALAN I. UMUM Untuk mencapai tujuan pembangunan nasional sebagaimana telah diatur dalam alinea ke-4 Undang-Undang Dasar Negara Republik Indonesia Tahun 1945, mewujudkan Wawasan Nusantara serta memantapkan ketahanan nasional, diperlukan sistem transportasi nasional yang memiliki posisi penting dan strategis dalam pembangunan nasional yang berwawasan lingkungan. Transportasi merupakan salah satu sarana untuk memperlancar roda perekonomian, membuka akses ke daerah pedalaman atau terpencil, memperkukuh persatuan dan kesatuan bangsa, menegakkan kedaulatan negara, serta mempengaruhi semua aspek kehidupan masyarakat yang dilaksanakan melalui penyelenggaraan Lalu Lintas dan Angkutan Jalan. Pentingnya penyelenggaraan Lalu Lintas dan Angkutan Jalan tercermin pada semakin meningkatnya kebutuhan jasa angkutan bagi mobilitas orang serta barang di dalam negeri, dari dan ke luar negeri, serta berperan sebagai pendorong, dan penggerak bagi pertumbuhan daerah dan pengembangan wilayah. Menyadari peran transportasi tersebut, penyelenggaraan Lalu Lintas dan Angkutan Jalan harus ditata dalam satu kesatuan sistem transportasi nasional secara terpadu dan mampu mewr.rjudkan penyediaan jasa transportasi yang seimbang dengan tingkat kebutuhan, selamat, aman, efektif, dan efisien. Undang-Undang Nomor 11 Tahun 2O2O tentang Cipta Kerja merupakan upaya Pemerintah Pusat untuk menciptakan dan memperluas lapangan kerja dalam rangka penurunan jumlah pengangguran dan menampung pekerja baru serta mendorong pengembangan koperasi dan usaha mikro, kecil, dan menengah dengan tujuan untuk meningkatkan perekonomian nasional yang akan dapat meningkatkan kesejahteraan masyarakat. Kebijakan . . . SK No 085095 A PRES IDEN REPUBLIK INDONES]A -2- Kebijakan dan langkah-langkah strategis Undang-Undang Nomor 11 Tahun 2O2O tentang Cipta Kerja yang memerlukan keterlibatan semua pihak yang terkait, dan terhadap hal tersebut perlu men5rusun dan menetapkan tindak lanjut dari Undang-Undang Nomor 11 Tahun 2O2O tentang Cipta Kerja dengan tujuan untuk menciptakan lapangan kerja yang seluas- luasnya bagi ralryat Indonesia secara merata di seluruh wilayah Negara Kesatuan Republik Indonesia dalam rangka memenuhi hak atas penghidupan yang layak. Untuk melaksanakan Undang-Undang Nomor 11 Tahun 2O2O tentang",
      "metadata": {
        "page_start": 6,
        "page_end": 7
      }
    },
    {
      "text": "yang layak. Untuk melaksanakan Undang-Undang Nomor 11 Tahun 2O2O tentang Cipta Kerja dan sebagai upaya untuk mendorong kemajuan penyelenggaraan Lalu Lintas dan Angkutan Jalan yaitu dilakukan dengan cara memberikan kemudahan berusaha untuk mendorong investasi di bidang penyelenggaraan Lalu Lintas dan Angkutan Jalan. Oleh karena itu, perlu dilakukan penyederhanaan terhadap proses pertzinan penyelenggaraan Lalu Lintas dan Angkutan Jalan. Peraturan Pemerintah ini mengatur antara lain mengenai ketentuan- ketentuan terkait analisis dampak Lalu Lintas, pengujian dan rancang bangun Kendaraan Bermotor, penyelenggaraan Terminal, Perizinan Berusaha bidang Lalu Lintas dan Angkutan Jalan serta subsidi penyelenggaraan angkutan, sebagaimana diamanatkan dalam Undang- Undang Nomor 11 Tahun 2O2O tentang Cipta Kerja. Dalam rangka menjamin keamanan, keselamatan, ketertiban, dan Kelancaran Lalu Lintas dan Angkutan Jalan, rencana pembangunan suatu pusat kegiatan wajib dilakukan analisis dampak Lalu Lintas sesuai dengan kategori skala dampak bangkitan Lalu Lintas yang ditimbulkan. Untuk memberikan kemudahan berusaha bagi para pelaku usaha, dokumen analisis dampak Lalu Lintas dimaksud terintegrasi dengan dokumen analisis mengenai dampak lingkungan hidup atau upaya pengelolaan lingkungan hidup dan upaya pemantauan lingkungan hidup. Peraturan Pemerintah ini telah menampung berbagai perubahan pengaturan yang terkait dengan penyelenggaraan pengujian dan rancang t\"rgul Kendaraan Bermotor. Hal ini dimaksudkan untuk meningkatkan kualitas kinerja pengujian Kendaraan Bermotor sekaligus kemudahan pelayanan kepada masyarakat sehingga dapat diwujudkan keselamatan sarana yang lebih baik. Penyelenggaraan pengujian Kendaraan Bermotor dapat dikerjasamakan badan usaha milik negara, badan usaha milik daerah, badan usaha milik desa, dan swasta. Dalam . . . SK No 085094A PRES IDEN REPUBLIK INDONESIA -3- Dalam rangka meningkatkan ekosistem investasi dan kegiatan berusaha, Pemerintah Pusat dan Pemerintah Daerah dapat bekerja sama dengan badan usaha milik negara, badan usaha milik daerah, badan usaha milik desa, koperasi, dan swasta dalam penyelenggaraan Terminal. Untuk memberikan kemudahan, pemberdayaan, dan perlindungan bagi usaha kecil dan mikro, pada fasilitas Terminal disediakan tempat untuk kegiatan usaha mikro dan kecil paling sedikit 3O% (tiga puluh persen). Untuk meningkatkan keamanan, keselamatan, ketertiban, dan Kelancaran Lalu Lintas dan Angkutan Jalan serta pengawasan angkutan barang di Jalan diatur adanya Perizinan Berusaha penyelenggaraan angkutan barang umum, dan agar selaras dengan Undang-Undang Nomor 1 1 Tahun 2O2O tentang Cipta Kerja yang bertujuan memberikan kemudahan berusaha dalam rangka percepatan cipta kerja, Perizinan Berusaha di bidang Lalu Lintas dan Angkutan Jalan dilakukan melalui Perrzinan Berusaha berbasis risiko sesuai norma, standar, prosedur dan kriteria yang ditetapkan Pemerintah Pusat. Pengaturan mengenai pemberian subsidi dalam Peraturan Pemerintah ini tidak hanya diberikan kepada angkutan Penumpang umum dengan Kendaraan Bermotor untuk tarif kelas ekonomi pada trayek tertentu tetapi juga diberikan kepada angkutan barang pada lintas tertentu dalam rangka mendukung program pemerintah khususnya pada wilayah tertinggal, terpencil, terluar, dan perbatasan. Berdasarkan hal tersebut di atas perlu ditetapkan Peraturan Pemerintah tentang Penyelenggaraan bidang Lalu Lintas dan Angkutan Jalan. II. PASAL DEMI PASAL Pasal 1 Cukup jelas. Pasal 2 Ayat ( 1) Yang dimaksud dengan \"rencana pembangunan pusat kegiatan, permukiman, dan infrastruktur\" adalah berupa pembangunan baru, pengembangan, atau peningkatan kepadatan. Gangguan . SK No 085093 A PRES I DEN REPUBLIK INDONESIA -4- Gangguan keamanan meliputi potensi gangguan keamanan yang diakibatkan oleh pembangunan pusat kegiatan, permukiman, dan",
      "metadata": {
        "page_start": 7,
        "page_end": 7
      }
    },
    {
      "text": "gangguan keamanan yang diakibatkan oleh pembangunan pusat kegiatan, permukiman, dan infrastruktur. Gangguan keselamatan apabila meningkatnya resiko terjadinya kecelakaan Lalu Lintas baik di ruas Jalan maupun persimPangan. Gangguan ketertiban meliputi potensi gangguan ketertiban yang diakibatkan oleh pembangunan pusat kegiatan, permukiman, dan infrastruktur. Gangguan kelancaran lalu lintas dan angkutan jalan meliputi menurunnya tingkat pelayanan LaIu Lintas' Ayat (2) Cukup jelas. Pasal 3 Cukup jelas. Pasal 4 Cukup jelas. Pasal 5 Cukup jelas. Pasal 6 Ayat (1) Huruf a Cukup jelas. Huruf b Cukup jelas. Huruf c Cukup jelas. Huruf d Cukup jelas. Huruf e . . SK No 085092A PRES IDEN REPUBLIK INDONESIA -5- Huruf e Cukup jelas Huruf f Cukup jelas Huruf g Huruf h Cukup jelas. Huruf i Cukup jelas. Huruf j Cukup jelas. Huruf kSimulasi kinerja Lalu Lintas dengan adanya pengembangan dalam hal ini dilakukan dengan menggunakan faktor trip rate yang ditetapkan seca-ra nasional berdasarkan jenis kegiatan yang dikembangkan, klasifikasi kota, dan faktor teknis lainnya. Simulasi kinerja Lalu Lintas dengan adanya pengembangan termasuk pula simulasi dan penanganan dampak Lalu Lintas yang diperkirakan akan timbul. Gambara-n umum lokasi yang akan dibangun atau dikembangkan paling sedikit memuat tentang kondisi fisik, kondisi sosial ekonomi, kondisi Lalu Lintas, dan pelayanan angkutan yang ada di lokasi yang akan dikembangkan. Ayat (21 Cukup jelas. Ayat (3) Cukup jelas. Pasal 7 Cukup jelas. SK No 093170 APasal 8 . PRES IDEN REPUBLIK TNDONESIA -6- Pasal Pasal Pasal Pasal Pasal Pasal Pasal Pasal Pasal Pasal8 Cukup jelas\" 9 Cukup jelas. 10 Cukup jelas. 11 Cukup jelas. T2 Cukup jelas. 13 Cukup jelas. t4 Cukup jelas. 15 Cukup jelas. t6 Ayat (1) Cukup jelas. Ayat (2) Yang dimaksud dengan \"dikalibrasi\" adalah suatu proses untuk menguji keakuratan pera-latan pengujian. t7 Ayat (1) Yang dimaksud d.engan \"swasta\" termasuk usaha mikro, kecil, dan menengah. Ayat (2) Cukup jelas. Ayat(3) ... SK No 093t71 A PRES I DEN REPUBLIK INDONESIA -7 - Ayat (3) Cukup jelas. Ayat (a) CukuP jelas' Ayat (5) CukuP jelas. Ayat (6) Cukup jelas. Ayat (7) CukuP jelas. Pasal 18 Cukup jelas. Pasal 19 Cukup jelas. Pasal 20 pasal ini berasal dari Pasal 131 Peraturan Pemerintah Nomor 55 Tahun 2Ol2 tentang Kendaraan (Lembaran Negara Republik Indonesia Tahun 2Ol2 Nomor l2O, Tambahan Lembaran Negara Republik Indonesia Nomor 5317). Ayat (1) Yang dimaksud dengan \"penelitian rancang bangun dan rekalrasa Kendaraan Bermotor\" adalah pemeriksaan secara teliti atas desain sesuai dengan persyaratan teknis' Huruf a yang dimaksud dengan \"rumah-rumah\" adalah bagian dari Kendaraan Bermotor, jenis mobil penumpang, mobil bus, mobil barang, atau sepeda motor yang berada pada landasan berbentuk ruang muatan untuk orang maupun barang. SK No 085091 AHuruf b PRES IDEN REPUBLIK INDONESIA -8- Huruf b Yang dimaksud dengan \"bak muatan\" adalah semua bentuk konstruksi bak muatan untuk angkutan barang yang bersifat padat, cair, atau gas yang terpasang pada landasan Kendaraan Bermotor. Huruf c Cukup jelas. Hurrrf d Cukup jelas. Huruf e Cukup jelas. Huruf f Modifikasi dimensi hanya dapat dilakukan pada perpanjangan atau pemendekan landasan (chassis) tanpa mengubah jarak sumbu dan konstruksi Kendaraan Bermotor tersebut. Modifikasi daya angkut hanya dapat",
      "metadata": {
        "page_start": 7,
        "page_end": 7
      }
    },
    {
      "text": "dan konstruksi Kendaraan Bermotor tersebut. Modifikasi daya angkut hanya dapat dilakukan pada Kendaraan Bermotor dengan menambah sumbu bagian belakang tanpa mengubah jarak sumbu aslinya dan sumbu yang ditambahkan harus memiliki material yang sama dengan sumbu aslinya dan harus dilakukan perhitungan sesuai dengan daya dukung Jalan yang dilalui. Ayat (2) Cukup jelas. Ayat (3) Cukup jelas. Pasal 2 1 Cukup jelas. SK No 085090 APasaL 22 PRES IDEN REPUBLIK INDONESIA -9 - Pasal22 Pasa-l PasalCukup jelas. 23 Pasal ini berasal dari Pasal 140 Peraturan Pemerintah Nomor 55 Tahun 2OI2 tentang Kendaraan (Lembaran Negara Republik Indonesia Tahun 2Ol2 Nomor l2O, Tambahan Lembaran Negara Republik Indonesia Nomor 5317). 24 Pasal ini berasal dari Pasal 143 Peraturan Pemerintah Nomor 55 Tahun 2AL2 tentang Kendaraan (Lembaran Negara Republik Indonesia Tahun 2072 Nomor l2O, Tambahan Lembaran Negara Republik Indonesia Nomor 5317). Ayat (1) Cukup jelas. Ayat (2) Cukup jelas. Ayat (3) Huruf a Cukup jelas. Huruf b Cukup jelas. Hur f c Yang dimaksud dengan \"unit pelaksana pengujian swasta\" adalah pihak swasta yang melakukan kegiatan khusus di bidang pengujian Kendaraan Bermotor atau bengkel unrum yang mempunyai akreditasi dan kua-litas tertentu untuk dapat melakukan uji'berkala Kendaraan Bermotor. Ayat (a) Cukup jelas. SK No 093174 AAya.t(5) .., PRES IDEN REPUBLIK lNDONES]A -10- Ayat (5) Cukup jelas. Ayat (6) Cukup jelas. Ayat (7) Cukup jelas. Pasal 25 Cukup jelas\" Pasal 26 Cukup jelas. Pasal 27 Cukup jelas. Pasal 28 Cukup jelas. Pasal 29 Cukup jelas. Pasal 30 Cukup jelas. Pasal 31 Cukup jelas. Pasal 32 Ayat (1) Permintaan angkutan didasarkan pada supplg dan demand. Ayat (2) Cukup jelas. Ayat (3) Cukup jelas. SK. Nlo 093175 AAyat(4) \".. PasaI Pasal Pasal Pasal Pasal 37PRES IDEN REPUBLIK INDONESIA - 11- Ayat (4) Cukup jelas\" 33 Cukup jelas. 34 Pasal ini berasal dari Pasal T0 Peraturan Pemerintah Nomor 79 Tahun 2013 tentang Jaringan Lalu Lintas dan Angkutan Jalan (Lembaran Negara Repubhk Indonesia Tahun 2Ot3 Nomor 193, Tambahan Lembaran Negara Republik Indonesia Nomor 5468). 35 Cukup jelas. 36 Ayat (1) Lingkungan kerja Terminal dalam ketentuan ini termasuk Jalan akses keluar masuk Terminal. Ayat (2) Cukup jelas. Ayat (3) Cukup jelas. Ayat (4) . Yang dimaksud dengan \"swasta\" termasuk usaha mikro, kecil, dan menengah. Ayat (5) Cukup j Pasal ini berasal dari Pasa-l 74 Peraturan Pemerintah Nomor 79 Tahun 2013 tentang Jaringan Lalu Lintas dan Angkutan Jalan (Lembaran Negara Republik Indonesia Tahun 2Ol3 Nomor 193, Tambahan Lembaran Negara Republik Indonesia Nomor 5468). SK No 093176 APasal38... PRES IDEN REPUBLIK INDONESIA -12- Pasal 38 Cukup jelas. Pasal 39 Ayat (1) Cukup jelas. Ayat (2) Yang dimaksud dengan \"swasta\" termasuk usaha mikro, kecil, dan menengah. Pasal 40 Pasal ini berasal dari PasaLT9 Peraturan Pemerintah Nomor 79 Tahun 2Ol3 tentang Jaringan La-lu Lintas dan Angkutan Jalan (Lembaran Negara Republik Indonesia Tahun 2Ol3 Nomor 193, Tambahan Lembaran Negara Republik Indonesia Nomor 5468). Ayat (1) Cukup jelas. Ayat (2) Cukup jelas. Ayat (3) Yang dimaksud dengan \"swasta\" termasuk usaha mikro, kecil, dan menengah. Pasal 41 Pasal ini berasal dari Pasal 81 Peraturan Pemerintah Nomor 79 Tahun 2Ol3 tentang Jaringan",
      "metadata": {
        "page_start": 7,
        "page_end": 8
      }
    },
    {
      "text": "Pasal 81 Peraturan Pemerintah Nomor 79 Tahun 2Ol3 tentang Jaringan Lalu Lintas dan Angkutan Jalan (Lembaran Negara Republik Indonesia Tahun 2Ol3 Nomor 193, Tambahan Lembaran Negara Republik Indonesia Nomor 5468). Pasal42 Cukup jelas. Pasal 43 Cukup jelas. SK No 093171 APasal 44 PRES I DEN REPUBLIK INDONESIA -13- Pasal 44 Pasal ini berasal dari Pasal 65 dan Pasa-l 67 Peraturan Pemerintah Nomor T4Tahun 2Ol4 tentang Angkutan Jalan (LembaranNegara Republik Indonesia Tahun 2Ol4 Nomor 260, Tarnbahan Lembaran Negara Republik Indonesia Nomor 5594). Pasal 45 Pasal ini berasal dari Pasal 68 Peraturan Pemerintah Nomor T4Tahun2014. tentang Angkutan Jalan (Lembaran Negara Republik lndonesia Tahun 2Ol4 Nomor 260, Tambahan Lembaran Negara Republik Indonesia Nomor 5594). Pasal 46 Cukup jelas\" Pasal47 Cukup jelas. Pasal 48 Cukup jelas. Pasai 49 Cukup jelas. Pasal 50 Cukup jelas. Pasal 51 Cukup jelas. Pasal 52 C jelas. Pasal 53 Cukup jelas. Pasal 54 Cukup jelas. SK No 093178 APasal55... PRES IDEN REPUBLIK INDONESIA -t4- Pasal 55 Cukup jelas. Pasal 56 Cukup jelas. Pasal 57 Cukup jelas. Pasal 58 Cukup jelas. Pasal 59 Cukup jelas. Pasal 60 Cukup jelas. Pasal 61 Cukup jelas. Pasal 62 Cukup jelas. TAMBAHAN LEMBARAN NEGARA REPUBLIK INDONESIA NOMOR 6642 SK No 085087 A",
      "metadata": {
        "page_start": 8,
        "page_end": 8
      }
    }
  ]
}